{"version":2,"kind":"Article","sha256":"dbbbb35c52b4fdcb1c00fcbf24f764257bc58cbd22e96fbdb343c3d72cbd95aa","slug":"sec-04-05-a-demonstration","location":"/src/content/chapter_4/sec_04-05-A-Demonstration.md","dependencies":[],"frontmatter":{"title":"A Demonstration","content_includes_title":false,"authors":[{"nameParsed":{"literal":"Benny Chin","given":"Benny","family":"Chin"},"name":"Benny Chin","affiliations":["GIS Unit, Geography, National University of Singapore"],"id":"contributors-myst-generated-uid-0"}],"license":{"content":{"id":"CC-BY-NC-ND-4.0","url":"https://creativecommons.org/licenses/by-nc-nd/4.0/","name":"Creative Commons Attribution Non Commercial No Derivatives 4.0 International","CC":true},"code":{"id":"MIT","url":"https://opensource.org/licenses/MIT","name":"MIT License","free":true,"osi":true}},"github":"https://github.com/wcchin/geo-stat-vis","keywords":["GIS","GIScience","Cartography","Spatial Analysis"],"copyright":"2025 National University of Singapore","affiliations":[{"id":"GIS Unit, Geography, National University of Singapore","name":"GIS Unit, Geography, National University of Singapore"}],"numbering":{"title":{"offset":1}},"source_url":"https://github.com/wcchin/geo-stat-vis/blob/main/src/content/chapter_4/sec_04-05-A-Demonstration.md","edit_url":"https://github.com/wcchin/geo-stat-vis/edit/main/src/content/chapter_4/sec_04-05-A-Demonstration.md","thumbnail":"/gordon_square2-3fe2d4569b7338896520ab0c94916a6d.png","exports":[{"format":"md","filename":"sec_04-05-A-Demonstration.md","url":"/sec_04-05-A-Demonstr-0c0e65e637d00952cd931978d16c5fcb.md"}]},"mdast":{"type":"root","children":[{"type":"block","children":[{"type":"container","kind":"figure","children":[{"type":"image","url":"/gordon_square2-3fe2d4569b7338896520ab0c94916a6d.png","alt":"Let’s do a mind travel to  Gordon Square, London, UK. Source: Google Map","align":"center","data":{"altTextIsAutoGenerated":true},"key":"I4lbri486Z","urlSource":"../resources/w05-img/gordon_square2.png"},{"type":"caption","children":[{"type":"paragraph","position":{"start":{"line":9,"column":1},"end":{"line":9,"column":1}},"children":[{"type":"text","value":"Let’s do a mind travel to  Gordon Square, London, UK. Source: ","position":{"start":{"line":9,"column":1},"end":{"line":9,"column":1}},"key":"WrirAaDSGZ"},{"type":"link","url":"https://maps.app.goo.gl/Qdb1K4hzyG485Btm8","position":{"start":{"line":9,"column":1},"end":{"line":9,"column":1}},"children":[{"type":"text","value":"Google Map","position":{"start":{"line":9,"column":1},"end":{"line":9,"column":1}},"key":"JEoi7B4yA4"}],"urlSource":"https://maps.app.goo.gl/Qdb1K4hzyG485Btm8","key":"uOC9jlL1YB"}],"key":"gboWAxHA3R"}],"key":"Zqp4eW3QNZ"}],"enumerator":"1","key":"JyFdVbRLWh"},{"type":"heading","depth":2,"position":{"start":{"line":13,"column":1},"end":{"line":13,"column":1}},"children":[{"type":"text","value":"The question","position":{"start":{"line":13,"column":1},"end":{"line":13,"column":1}},"key":"qMuJtUzFjy"}],"identifier":"the-question","label":"The question","html_id":"the-question","implicit":true,"key":"PoboWWQve2"},{"type":"list","ordered":false,"spread":false,"position":{"start":{"line":15,"column":1},"end":{"line":20,"column":1}},"children":[{"type":"listItem","spread":true,"position":{"start":{"line":15,"column":1},"end":{"line":15,"column":1}},"children":[{"type":"paragraph","position":{"start":{"line":15,"column":1},"end":{"line":15,"column":1}},"children":[{"type":"text","value":"Can we assume people randomly find a spot to sit?","position":{"start":{"line":15,"column":1},"end":{"line":15,"column":1}},"key":"fsbPAepHch"}],"key":"PCN90CiCz1"}],"key":"xVpUt4345K"},{"type":"listItem","spread":true,"position":{"start":{"line":16,"column":1},"end":{"line":16,"column":1}},"children":[{"type":"paragraph","position":{"start":{"line":16,"column":1},"end":{"line":16,"column":1}},"children":[{"type":"text","value":"Can we assume people prefer not to sit too close to strangers?","position":{"start":{"line":16,"column":1},"end":{"line":16,"column":1}},"key":"y4Irn73gfI"}],"key":"pLsxGr55Y0"}],"key":"bzdvv622Kv"},{"type":"listItem","spread":true,"position":{"start":{"line":17,"column":1},"end":{"line":18,"column":1}},"children":[{"type":"paragraph","position":{"start":{"line":17,"column":1},"end":{"line":17,"column":1}},"children":[{"type":"text","value":"If they go with friends or colleagues, they will sit together.","position":{"start":{"line":17,"column":1},"end":{"line":17,"column":1}},"key":"cLPC9kU5Wl"}],"key":"lQELEBiDR1"}],"key":"nFP4cjHUil"},{"type":"listItem","spread":true,"position":{"start":{"line":19,"column":1},"end":{"line":20,"column":1}},"children":[{"type":"paragraph","position":{"start":{"line":19,"column":1},"end":{"line":19,"column":1}},"children":[{"type":"emphasis","position":{"start":{"line":19,"column":1},"end":{"line":19,"column":1}},"children":[{"type":"text","value":"Will the process of .red[people finding comfortable spots for sitting in an open space] result in a random, clustered, or dispersed pattern?","position":{"start":{"line":19,"column":1},"end":{"line":19,"column":1}},"key":"D0ZEW1sZjd"}],"key":"yVxTHASiGc"}],"key":"F8O6LroRPN"}],"key":"UwLcRdXNWh"}],"key":"HKKo4XVYrT"},{"type":"paragraph","position":{"start":{"line":21,"column":1},"end":{"line":21,"column":1}},"children":[{"type":"text","value":"Analyze with:","position":{"start":{"line":21,"column":1},"end":{"line":21,"column":1}},"key":"NG65YyiRtG"}],"key":"kZKRPJxFCf"},{"type":"list","ordered":true,"start":1,"spread":false,"position":{"start":{"line":22,"column":1},"end":{"line":25,"column":1}},"children":[{"type":"listItem","spread":true,"position":{"start":{"line":22,"column":1},"end":{"line":22,"column":1}},"children":[{"type":"paragraph","children":[{"type":"text","value":"individual level","position":{"start":{"line":22,"column":1},"end":{"line":22,"column":1}},"key":"qsbFqScb35"}],"key":"rbLdUkkTqH"}],"key":"H1ak7Bz2sl"},{"type":"listItem","spread":true,"position":{"start":{"line":23,"column":1},"end":{"line":25,"column":1}},"children":[{"type":"paragraph","children":[{"type":"text","value":"group level","position":{"start":{"line":23,"column":1},"end":{"line":23,"column":1}},"key":"IaB0l5DQLF"}],"key":"r6Uswkv8eM"}],"key":"oBgoceyDL9"}],"key":"WJDaB3pUfP"},{"type":"heading","depth":2,"position":{"start":{"line":26,"column":1},"end":{"line":26,"column":1}},"children":[{"type":"text","value":"The dataset","position":{"start":{"line":26,"column":1},"end":{"line":26,"column":1}},"key":"x3osw3YOoP"}],"identifier":"the-dataset","label":"The dataset","html_id":"the-dataset","implicit":true,"key":"Xwy1mv8gsJ"},{"type":"paragraph","position":{"start":{"line":28,"column":1},"end":{"line":28,"column":1}},"children":[{"type":"text","value":"This dataset records the location of people sitting on a grass patch in Gordon Square, London, at 3pm on a sunny afternoon.","position":{"start":{"line":28,"column":1},"end":{"line":28,"column":1}},"key":"mjhQ1A0Okd"}],"key":"dycXZLM4S4"},{"type":"paragraph","position":{"start":{"line":30,"column":1},"end":{"line":30,"column":1}},"children":[{"type":"text","value":"Area: ","position":{"start":{"line":30,"column":1},"end":{"line":30,"column":1}},"key":"nZFMwwtBxx"},{"type":"inlineMath","value":"42 \\times 56 \\text{m}^2","position":{"start":{"line":30,"column":1},"end":{"line":30,"column":1}},"html":"<span class=\"katex\"><span class=\"katex-mathml\"><math xmlns=\"http://www.w3.org/1998/Math/MathML\"><semantics><mrow><mn>42</mn><mo>×</mo><mn>56</mn><msup><mtext>m</mtext><mn>2</mn></msup></mrow><annotation encoding=\"application/x-tex\">42 \\times 56 \\text{m}^2</annotation></semantics></math></span><span class=\"katex-html\" aria-hidden=\"true\"><span class=\"base\"><span class=\"strut\" style=\"height:0.7278em;vertical-align:-0.0833em;\"></span><span class=\"mord\">42</span><span class=\"mspace\" style=\"margin-right:0.2222em;\"></span><span class=\"mbin\">×</span><span class=\"mspace\" style=\"margin-right:0.2222em;\"></span></span><span class=\"base\"><span class=\"strut\" style=\"height:0.8141em;\"></span><span class=\"mord\">56</span><span class=\"mord\"><span class=\"mord text\"><span class=\"mord\">m</span></span><span class=\"msupsub\"><span class=\"vlist-t\"><span class=\"vlist-r\"><span class=\"vlist\" style=\"height:0.8141em;\"><span style=\"top:-3.063em;margin-right:0.05em;\"><span class=\"pstrut\" style=\"height:2.7em;\"></span><span class=\"sizing reset-size6 size3 mtight\"><span class=\"mord mtight\">2</span></span></span></span></span></span></span></span></span></span></span>","key":"PqYURsMwGO"}],"key":"YGhUMA7aVA"},{"type":"paragraph","position":{"start":{"line":32,"column":1},"end":{"line":32,"column":1}},"children":[{"type":"text","value":"Source: ","position":{"start":{"line":32,"column":1},"end":{"line":32,"column":1}},"key":"r2xV1RfJ8x"},{"type":"link","url":"https://search.r-project.org/CRAN/refmans/spatstat.data/html/gordon.html","position":{"start":{"line":32,"column":1},"end":{"line":32,"column":1}},"children":[{"type":"text","value":"R spatstat dataset","position":{"start":{"line":32,"column":1},"end":{"line":32,"column":1}},"key":"X1alvtxQoN"}],"urlSource":"https://search.r-project.org/CRAN/refmans/spatstat.data/html/gordon.html","key":"efHveIbkxM"},{"type":"text","value":", Baddeley et al. 2013: ","position":{"start":{"line":32,"column":1},"end":{"line":32,"column":1}},"key":"n0l3DacszT"},{"type":"link","url":"https://www.jstatsoft.org/article/view/v055i11","position":{"start":{"line":32,"column":1},"end":{"line":32,"column":1}},"children":[{"type":"text","value":"DOI:10​.18637​/jss​.v055​.i11","position":{"start":{"line":32,"column":1},"end":{"line":32,"column":1}},"key":"SXSru1NAyt"}],"urlSource":"https://www.jstatsoft.org/article/view/v055i11","key":"tVu7HKatv0"}],"key":"bzt4DCKBLv"},{"type":"container","kind":"figure","children":[{"type":"image","url":"/GordonSquare_individ-b5eee8261c97057b12e0fce3c4392c0b.png","alt":"Distribution of individuals and groups.","align":"center","data":{"altTextIsAutoGenerated":true},"key":"dYYa0KdviK","urlSource":"../resources/w05-img/GordonSquare_individual_and_groups_xkcd.png"},{"type":"caption","children":[{"type":"paragraph","position":{"start":{"line":40,"column":1},"end":{"line":40,"column":1}},"children":[{"type":"text","value":"Distribution of individuals and groups.","position":{"start":{"line":40,"column":1},"end":{"line":40,"column":1}},"key":"GyrAkEXWYW"}],"key":"koNW0eTEme"}],"key":"EXeT81uYLX"}],"enumerator":"2","key":"fuJJmKySBg"},{"type":"heading","depth":2,"position":{"start":{"line":44,"column":1},"end":{"line":44,"column":1}},"children":[{"type":"text","value":"Nearest Neighbor Analysis","position":{"start":{"line":44,"column":1},"end":{"line":44,"column":1}},"key":"TnVJuz7txD"}],"identifier":"nearest-neighbor-analysis","label":"Nearest Neighbor Analysis","html_id":"nearest-neighbor-analysis","implicit":true,"key":"PpSUCGi6pC"},{"type":"list","ordered":false,"spread":false,"position":{"start":{"line":46,"column":1},"end":{"line":50,"column":1}},"children":[{"type":"listItem","spread":true,"position":{"start":{"line":46,"column":1},"end":{"line":46,"column":1}},"children":[{"type":"paragraph","children":[{"type":"text","value":"For individual, the p-value is significant with a negative z-score, indicating people tended to sit together.","position":{"start":{"line":46,"column":1},"end":{"line":46,"column":1}},"key":"MkPUE1f3aj"}],"key":"WJgZWCpk2o"}],"key":"nCqTbgA7Rq"},{"type":"listItem","spread":true,"position":{"start":{"line":47,"column":1},"end":{"line":50,"column":1}},"children":[{"type":"paragraph","children":[{"type":"text","value":"For in-group, the p-value is significant, with a positive z-score, suggesting the locations of groups are dispersed.","position":{"start":{"line":47,"column":1},"end":{"line":47,"column":1}},"key":"UmUfJEjjfU"}],"key":"QUNoLx2XRm"}],"key":"IsAnkOUkO8"}],"key":"CC3MxGIUWK"},{"type":"container","kind":"figure","children":[{"type":"image","url":"/nna_compare_hist_gor-a5f4060f86a826b6667ccd4a861ee75d.png","alt":"NNA result.","align":"center","data":{"altTextIsAutoGenerated":true},"key":"evMZ2OyRRC","urlSource":"../resources/w05-img/nna_compare_hist_gordon.png"},{"type":"caption","children":[{"type":"paragraph","position":{"start":{"line":56,"column":1},"end":{"line":56,"column":1}},"children":[{"type":"text","value":"NNA result.","position":{"start":{"line":56,"column":1},"end":{"line":56,"column":1}},"key":"TrTqKnGzNM"}],"key":"dPzhctZndW"}],"key":"G7MrygDKic"}],"enumerator":"3","key":"WQxXPl84dP"},{"type":"heading","depth":2,"position":{"start":{"line":60,"column":1},"end":{"line":60,"column":1}},"children":[{"type":"text","value":"Ripley’s K-function","position":{"start":{"line":60,"column":1},"end":{"line":60,"column":1}},"key":"bDO46AHqWj"}],"identifier":"ripleys-k-function","label":"Ripley’s K-function","html_id":"ripleys-k-function","implicit":true,"key":"AcaCsmnlI3"},{"type":"paragraph","position":{"start":{"line":62,"column":1},"end":{"line":62,"column":1}},"children":[{"type":"text","value":"For individual,","position":{"start":{"line":62,"column":1},"end":{"line":62,"column":1}},"key":"BRO7zEVbL9"}],"key":"Q455KE8kIp"},{"type":"list","ordered":false,"spread":false,"position":{"start":{"line":63,"column":1},"end":{"line":66,"column":1}},"children":[{"type":"listItem","spread":true,"position":{"start":{"line":63,"column":1},"end":{"line":63,"column":1}},"children":[{"type":"paragraph","children":[{"type":"text","value":"radius 4 m resulted in higher than random, indicating people tended to sit together at this scale.","position":{"start":{"line":63,"column":1},"end":{"line":63,"column":1}},"key":"yEfw0j1czl"}],"key":"ZCru9iSFCe"}],"key":"zkUTW19T5a"},{"type":"listItem","spread":true,"position":{"start":{"line":64,"column":1},"end":{"line":66,"column":1}},"children":[{"type":"paragraph","children":[{"type":"text","value":"betwen 4 m and 6 m , the observed line is near to the random, but still above the 95% CI.","position":{"start":{"line":64,"column":1},"end":{"line":64,"column":1}},"key":"kbmwP7K0zD"}],"key":"d2VDPVXyDr"}],"key":"as4H0rGDoR"}],"key":"T0HzysOQXy"},{"type":"paragraph","position":{"start":{"line":67,"column":1},"end":{"line":67,"column":1}},"children":[{"type":"text","value":"For in-group,","position":{"start":{"line":67,"column":1},"end":{"line":67,"column":1}},"key":"Zu81ZgMtmF"}],"key":"w4xwvI4cXe"},{"type":"list","ordered":false,"spread":false,"position":{"start":{"line":68,"column":1},"end":{"line":72,"column":1}},"children":[{"type":"listItem","spread":true,"position":{"start":{"line":68,"column":1},"end":{"line":68,"column":1}},"children":[{"type":"paragraph","children":[{"type":"text","value":"the search radius less than 7 m resulted in dispersed pattern.","position":{"start":{"line":68,"column":1},"end":{"line":68,"column":1}},"key":"tZMVF31NNt"}],"key":"kxf5oeAQP3"}],"key":"ckPJSA46Mb"},{"type":"listItem","spread":true,"position":{"start":{"line":69,"column":1},"end":{"line":72,"column":1}},"children":[{"type":"paragraph","children":[{"type":"text","value":"the search radius beyond 8 m presented random pattern.","position":{"start":{"line":69,"column":1},"end":{"line":69,"column":1}},"key":"KobVPAV5Q9"}],"key":"PDMdDdZL06"}],"key":"ZDGzsZQ2Bu"}],"key":"eQbYnjELe8"},{"type":"container","kind":"figure","children":[{"type":"image","url":"/k_function_ci_gordon-67981aa35bd9059b7292af96ff8fb9d1.png","alt":"K-function result.","align":"center","data":{"altTextIsAutoGenerated":true},"key":"R60va1cgyW","urlSource":"../resources/w05-img/k_function_ci_gordon.png"},{"type":"caption","children":[{"type":"paragraph","position":{"start":{"line":78,"column":1},"end":{"line":78,"column":1}},"children":[{"type":"text","value":"K-function result.","position":{"start":{"line":78,"column":1},"end":{"line":78,"column":1}},"key":"sDderjlmm9"}],"key":"ewpqUr0HQd"}],"key":"IvhmUOnTIp"}],"enumerator":"4","key":"kkSXVNHU6t"},{"type":"heading","depth":2,"position":{"start":{"line":83,"column":1},"end":{"line":83,"column":1}},"children":[{"type":"text","value":"Closing Remarks","position":{"start":{"line":83,"column":1},"end":{"line":83,"column":1}},"key":"MkYy1DsKXn"}],"identifier":"closing-remarks","label":"Closing Remarks","html_id":"closing-remarks","implicit":true,"key":"RwAIgSH4qB"},{"type":"heading","depth":3,"position":{"start":{"line":85,"column":1},"end":{"line":85,"column":1}},"children":[{"type":"text","value":"NNA & K-function: Key Considerations, Limitations, and Directions","position":{"start":{"line":85,"column":1},"end":{"line":85,"column":1}},"key":"IGyz1u0Xoh"}],"identifier":"nna-k-function-key-considerations-limitations-and-directions","label":"NNA & K-function: Key Considerations, Limitations, and Directions","html_id":"nna-k-function-key-considerations-limitations-and-directions","implicit":true,"key":"f6nsPvkkLW"},{"type":"paragraph","position":{"start":{"line":87,"column":1},"end":{"line":87,"column":1}},"children":[{"type":"strong","position":{"start":{"line":87,"column":1},"end":{"line":87,"column":1}},"children":[{"type":"text","value":"Sensitive to study area size and settings","position":{"start":{"line":87,"column":1},"end":{"line":87,"column":1}},"key":"Dx3RD5kEg6"}],"key":"HujM2B33rF"},{"type":"text","value":":","position":{"start":{"line":87,"column":1},"end":{"line":87,"column":1}},"key":"B30TxmUdEN"}],"key":"TLvX4l3na1"},{"type":"paragraph","position":{"start":{"line":89,"column":1},"end":{"line":89,"column":1}},"children":[{"type":"text","value":"CSR assume points to be scattered all around the study area. Thus, Ripley’s K function can be influenced by the size and shape of the study area. ","position":{"start":{"line":89,"column":1},"end":{"line":89,"column":1}},"key":"YUTZkq8lgn"},{"type":"emphasis","position":{"start":{"line":89,"column":1},"end":{"line":89,"column":1}},"children":[{"type":"text","value":"Larger study areas","position":{"start":{"line":89,"column":1},"end":{"line":89,"column":1}},"key":"cLO2tlgNSs"}],"key":"yO09ZG1h2h"},{"type":"text","value":" may result in different K function estimates compared to smaller ones, and ","position":{"start":{"line":89,"column":1},"end":{"line":89,"column":1}},"key":"xErO5PCDHv"},{"type":"emphasis","position":{"start":{"line":89,"column":1},"end":{"line":89,"column":1}},"children":[{"type":"text","value":"irregular shapes","position":{"start":{"line":89,"column":1},"end":{"line":89,"column":1}},"key":"VXt0qha6vp"}],"key":"LqquNO0j9H"},{"type":"text","value":" can introduce biases. Additionally, the settings used for the K function analysis, such as the bandwidth or edge correction method, can impact the results.","position":{"start":{"line":89,"column":1},"end":{"line":89,"column":1}},"key":"fqoQ6Pk3lJ"}],"key":"SErZqbkxXp"},{"type":"container","kind":"figure","children":[{"type":"image","url":"/area_size-eb92d8f10c1cde9d432261289cee3ef2.png","alt":"Effect of different area.","align":"center","data":{"altTextIsAutoGenerated":true},"key":"w2rgPt4AmK","urlSource":"../resources/w05-img/area_size.png"},{"type":"caption","children":[{"type":"paragraph","position":{"start":{"line":97,"column":1},"end":{"line":97,"column":1}},"children":[{"type":"text","value":"Effect of different area.","position":{"start":{"line":97,"column":1},"end":{"line":97,"column":1}},"key":"rQKiwLbkNn"}],"key":"kOtjbEQS3g"}],"key":"Xkro2hd2J8"}],"enumerator":"5","key":"gFNpS7aWwg"},{"type":"paragraph","position":{"start":{"line":101,"column":1},"end":{"line":101,"column":1}},"children":[{"type":"strong","position":{"start":{"line":101,"column":1},"end":{"line":101,"column":1}},"children":[{"type":"text","value":"Edge effect","position":{"start":{"line":101,"column":1},"end":{"line":101,"column":1}},"key":"woOH575Nxi"}],"key":"GlI44xyyZh"},{"type":"text","value":" (border effect):","position":{"start":{"line":101,"column":1},"end":{"line":101,"column":1}},"key":"QQAIR2M2zd"}],"key":"yjZEwP0zgP"},{"type":"paragraph","position":{"start":{"line":103,"column":1},"end":{"line":103,"column":1}},"children":[{"type":"text","value":"Points beyond the study area are ‘ignored.’ ","position":{"start":{"line":103,"column":1},"end":{"line":103,"column":1}},"key":"VRdYHyQqm9"},{"type":"emphasis","position":{"start":{"line":103,"column":1},"end":{"line":103,"column":1}},"children":[{"type":"text","value":"Points close to the boundary of the study area may have fewer neighboring points","position":{"start":{"line":103,"column":1},"end":{"line":103,"column":1}},"key":"mTe7Oyc7tC"}],"key":"tJp14IpmPB"},{"type":"text","value":" than those in the interior, which can bias the K function estimates. This is known as the edge effect, and it can introduce inaccuracies when studying spatial patterns. Edge correction methods are often employed to mitigate this issue.","position":{"start":{"line":103,"column":1},"end":{"line":103,"column":1}},"key":"B9Judgrj39"}],"key":"SHnKHSzdUg"},{"type":"container","kind":"figure","children":[{"type":"image","url":"/edge_effect-a5dedda7161711bf83d3bc48f7712b56.png","alt":"Edge Effect.","align":"center","data":{"altTextIsAutoGenerated":true},"key":"jfqafC8SO8","urlSource":"../resources/w05-img/edge_effect.png"},{"type":"caption","children":[{"type":"paragraph","position":{"start":{"line":111,"column":1},"end":{"line":111,"column":1}},"children":[{"type":"text","value":"Edge Effect.","position":{"start":{"line":111,"column":1},"end":{"line":111,"column":1}},"key":"nuxwdhj9WL"}],"key":"rAZthLkdIL"}],"key":"H4wgbOVQlo"}],"enumerator":"6","key":"g2WKckcOag"},{"type":"paragraph","position":{"start":{"line":115,"column":1},"end":{"line":115,"column":1}},"children":[{"type":"strong","position":{"start":{"line":115,"column":1},"end":{"line":115,"column":1}},"children":[{"type":"text","value":"Population-at-risk","position":{"start":{"line":115,"column":1},"end":{"line":115,"column":1}},"key":"i2Daoq4kr6"}],"key":"XngGXNNmJN"},{"type":"text","value":":","position":{"start":{"line":115,"column":1},"end":{"line":115,"column":1}},"key":"yjhwI64NJc"}],"key":"sk28hWhUWE"},{"type":"paragraph","position":{"start":{"line":117,"column":1},"end":{"line":117,"column":1}},"children":[{"type":"text","value":"Ripley’s K function assumes that the underlying point process is ","position":{"start":{"line":117,"column":1},"end":{"line":117,"column":1}},"key":"bkOK2ohwBt"},{"type":"emphasis","position":{"start":{"line":117,"column":1},"end":{"line":117,"column":1}},"children":[{"type":"text","value":"stationary and homogeneous","position":{"start":{"line":117,"column":1},"end":{"line":117,"column":1}},"key":"yD2cLfurgZ"}],"key":"JeAyhen0K0"},{"type":"text","value":". If the population at risk (i.e., the underlying risk of events occurring) is not uniform across the study area, this can violate the assumptions and lead to misleading results. Incorporating information on the population at risk can help refine the analysis and improve the accuracy of the conclusions drawn from the K function.","position":{"start":{"line":117,"column":1},"end":{"line":117,"column":1}},"key":"FOnQrJsMlJ"}],"key":"UTcJfnOyHN"},{"type":"container","kind":"figure","children":[{"type":"image","url":"/pop_at_risk-11f34768675e6bbfb59c56b60311d701.png","alt":"Population at risk.","align":"center","data":{"altTextIsAutoGenerated":true},"key":"P5C3HEiA26","urlSource":"../resources/w05-img/pop_at_risk.png"},{"type":"caption","children":[{"type":"paragraph","position":{"start":{"line":124,"column":1},"end":{"line":124,"column":1}},"children":[{"type":"text","value":"Population at risk.","position":{"start":{"line":124,"column":1},"end":{"line":124,"column":1}},"key":"aFk4r3LeCh"}],"key":"QbFsXD0Me4"}],"key":"Lwt3ElzYQn"}],"enumerator":"7","key":"UMxRX2ujUc"},{"type":"heading","depth":2,"position":{"start":{"line":128,"column":1},"end":{"line":128,"column":1}},"children":[{"type":"text","value":"What has been covered in this chapter and section?","position":{"start":{"line":128,"column":1},"end":{"line":128,"column":1}},"key":"xynW2suSWJ"}],"identifier":"what-has-been-covered-in-this-chapter-and-section","label":"What has been covered in this chapter and section?","html_id":"what-has-been-covered-in-this-chapter-and-section","implicit":true,"key":"UY6BxOBRcO"},{"type":"paragraph","position":{"start":{"line":130,"column":1},"end":{"line":130,"column":1}},"children":[{"type":"text","value":"What is the workflow of analyzing spatial point pattern?","position":{"start":{"line":130,"column":1},"end":{"line":130,"column":1}},"key":"erpnZxOxP8"}],"key":"cu1x7kWVfv"},{"type":"paragraph","position":{"start":{"line":132,"column":1},"end":{"line":132,"column":1}},"children":[{"type":"text","value":"Global Pattern: the overall pattern of the point distribution","position":{"start":{"line":132,"column":1},"end":{"line":132,"column":1}},"key":"hihqlVNwV1"}],"key":"xA01krNFcJ"},{"type":"paragraph","position":{"start":{"line":134,"column":1},"end":{"line":134,"column":1}},"children":[{"type":"text","value":"Local Pattern: where are the clusters","position":{"start":{"line":134,"column":1},"end":{"line":134,"column":1}},"key":"aP4Jn0LvGA"}],"key":"WZ3k679FcM"},{"type":"container","kind":"figure","children":[{"type":"image","url":"/about_point_pattern_-ec9eaeebf97e731903970ae358fa9149.png","alt":"Point pattern analysis.","align":"center","data":{"altTextIsAutoGenerated":true},"key":"vgaKYPltuB","urlSource":"../resources/w05-img/about_point_pattern_analysis Diagram.drawio.png"},{"type":"caption","children":[{"type":"paragraph","position":{"start":{"line":142,"column":1},"end":{"line":142,"column":1}},"children":[{"type":"text","value":"Point pattern analysis.","position":{"start":{"line":142,"column":1},"end":{"line":142,"column":1}},"key":"ezj7dSPdZ5"}],"key":"Sn0CEPNWBf"}],"key":"Cpj9Efn2w8"}],"enumerator":"8","key":"PbivLmGfEJ"},{"type":"heading","depth":2,"position":{"start":{"line":148,"column":1},"end":{"line":148,"column":1}},"children":[{"type":"text","value":"Some notes","position":{"start":{"line":148,"column":1},"end":{"line":148,"column":1}},"key":"fl60kS20NI"}],"identifier":"some-notes","label":"Some notes","html_id":"some-notes","implicit":true,"key":"JwNZ1FUdSH"},{"type":"paragraph","position":{"start":{"line":150,"column":1},"end":{"line":150,"column":1}},"children":[{"type":"text","value":"The three methods explore the spatial pattern with different angle:","position":{"start":{"line":150,"column":1},"end":{"line":150,"column":1}},"key":"VtJA5yZBbF"}],"key":"lc2BeWWRcl"},{"type":"list","ordered":false,"spread":false,"position":{"start":{"line":151,"column":1},"end":{"line":154,"column":1}},"children":[{"type":"listItem","spread":true,"position":{"start":{"line":151,"column":1},"end":{"line":151,"column":1}},"children":[{"type":"paragraph","children":[{"type":"text","value":"Quadrat count: the number of points fall in equal size quadrats","position":{"start":{"line":151,"column":1},"end":{"line":151,"column":1}},"key":"Oyjq1AuRqP"}],"key":"JVkHSu3kda"}],"key":"JpqVePwVeM"},{"type":"listItem","spread":true,"position":{"start":{"line":152,"column":1},"end":{"line":152,"column":1}},"children":[{"type":"paragraph","children":[{"type":"text","value":"NNA: how near/far the nearest neighbor is","position":{"start":{"line":152,"column":1},"end":{"line":152,"column":1}},"key":"p331cfO3QK"}],"key":"D2ONRLEmRm"}],"key":"umBs0mOuvD"},{"type":"listItem","spread":true,"position":{"start":{"line":153,"column":1},"end":{"line":154,"column":1}},"children":[{"type":"paragraph","children":[{"type":"text","value":"K-function: how many other points could be found for a specific search radius","position":{"start":{"line":153,"column":1},"end":{"line":153,"column":1}},"key":"KThMsjYPhQ"}],"key":"aqkEWcbn6V"}],"key":"ddRKD5pTQY"}],"key":"Bs3BeW6QYV"},{"type":"paragraph","position":{"start":{"line":155,"column":1},"end":{"line":155,"column":1}},"children":[{"type":"text","value":"The latter two methods can be extended:","position":{"start":{"line":155,"column":1},"end":{"line":155,"column":1}},"key":"ZSxyflpzpS"}],"key":"vN7wnquIiC"},{"type":"list","ordered":false,"spread":false,"position":{"start":{"line":156,"column":1},"end":{"line":158,"column":1}},"children":[{"type":"listItem","spread":true,"position":{"start":{"line":156,"column":1},"end":{"line":156,"column":1}},"children":[{"type":"paragraph","children":[{"type":"text","value":"NNA: to k-order nearest neighbor (see: ","position":{"start":{"line":156,"column":1},"end":{"line":156,"column":1}},"key":"htdMaczzKT"},{"type":"link","url":"https://www.ojp.gov/pdffiles1/nij/grants/209264.pdf","position":{"start":{"line":156,"column":1},"end":{"line":156,"column":1}},"children":[{"type":"text","value":"CrimeStat III","position":{"start":{"line":156,"column":1},"end":{"line":156,"column":1}},"key":"nkyOGJSAmI"}],"urlSource":"https://www.ojp.gov/pdffiles1/nij/grants/209264.pdf","key":"k2cxrD94lL"},{"type":"text","value":")","position":{"start":{"line":156,"column":1},"end":{"line":156,"column":1}},"key":"wBATsT0nul"}],"key":"H3YbDUjIbb"}],"key":"VityVcuR4s"},{"type":"listItem","spread":true,"position":{"start":{"line":157,"column":1},"end":{"line":158,"column":1}},"children":[{"type":"paragraph","children":[{"type":"text","value":"K-function: weighted K-function (see: ","position":{"start":{"line":157,"column":1},"end":{"line":157,"column":1}},"key":"am4fEgFNSS"},{"type":"link","url":"https://pro.arcgis.com/en/pro-app/3.1/tool-reference/spatial-statistics/h-how-multi-distance-spatial-cluster-analysis-ripl.htm","position":{"start":{"line":157,"column":1},"end":{"line":157,"column":1}},"children":[{"type":"text","value":"ArcGIS Pro","position":{"start":{"line":157,"column":1},"end":{"line":157,"column":1}},"key":"rNgLhKXbZc"}],"urlSource":"https://pro.arcgis.com/en/pro-app/3.1/tool-reference/spatial-statistics/h-how-multi-distance-spatial-cluster-analysis-ripl.htm","key":"OTdl32QFZJ"},{"type":"text","value":"])","position":{"start":{"line":157,"column":1},"end":{"line":157,"column":1}},"key":"pI2XY3HtrL"}],"key":"MHZRFjbkia"}],"key":"ssRWvkzMOj"}],"key":"my8wKuTCvP"},{"type":"paragraph","position":{"start":{"line":159,"column":1},"end":{"line":159,"column":1}},"children":[{"type":"text","value":"Things to considered:","position":{"start":{"line":159,"column":1},"end":{"line":159,"column":1}},"key":"D1FE9FGxW4"}],"key":"XkgOw6yHkt"},{"type":"list","ordered":false,"spread":false,"position":{"start":{"line":160,"column":1},"end":{"line":164,"column":1}},"children":[{"type":"listItem","spread":true,"position":{"start":{"line":160,"column":1},"end":{"line":160,"column":1}},"children":[{"type":"paragraph","children":[{"type":"text","value":"Edge effect: the near border areas could be underestimated due to the external points. (see: .smaller[","position":{"start":{"line":160,"column":1},"end":{"line":160,"column":1}},"key":"uPd84YvJS8"},{"type":"cite","url":"https://doi.org/10.2307/3237072","position":{"start":{"line":160,"column":1},"end":{"line":160,"column":1}},"children":[{"type":"text","value":"DOI:10.2307/3237072","position":{"start":{"line":160,"column":1},"end":{"line":160,"column":1}},"key":"UJCxTiP3ua"}],"kind":"narrative","label":"Goreaud_1999","identifier":"https://doi.org/10.2307/3237072","enumerator":"1","key":"Ev1cBoyPFy"},{"type":"text","value":"])","position":{"start":{"line":160,"column":1},"end":{"line":160,"column":1}},"key":"SP9BH955aX"}],"key":"iOXNDG52WO"}],"key":"n3YLs2dBhu"},{"type":"listItem","spread":true,"position":{"start":{"line":161,"column":1},"end":{"line":164,"column":1}},"children":[{"type":"paragraph","children":[{"type":"text","value":"Population at risk: a place with more population could have more events (e.g., crime/disease cases) happens by chance. (see: ","position":{"start":{"line":161,"column":1},"end":{"line":161,"column":1}},"key":"E3aj0UPbHf"},{"type":"emphasis","position":{"start":{"line":161,"column":1},"end":{"line":161,"column":1}},"children":[{"type":"text","value":"SaTScan","position":{"start":{"line":161,"column":1},"end":{"line":161,"column":1}},"key":"yE2iXJtNuZ"}],"key":"A3CEFxndXW"},{"type":"text","value":"(","position":{"start":{"line":161,"column":1},"end":{"line":161,"column":1}},"key":"bLq3zkJork"},{"type":"link","url":"https://www.satscan.org/cgi-bin/satscan/register.pl/SaTScan_Users_Guide.pdf?todo=process_userguide_download","position":{"start":{"line":161,"column":1},"end":{"line":161,"column":1}},"children":[{"type":"text","value":"https://​www​.satscan​.org​/cgi​-bin​/satscan​/register​.pl​/SaTScan​_Users​_Guide​.pdf​?todo​=​process​_userguide​_download","position":{"start":{"line":161,"column":1},"end":{"line":161,"column":1}},"key":"YN0SSKu4Eb"}],"urlSource":"https://www.satscan.org/cgi-bin/satscan/register.pl/SaTScan_Users_Guide.pdf?todo=process_userguide_download","key":"VpmbqFvKDM"},{"type":"text","value":")","position":{"start":{"line":161,"column":1},"end":{"line":161,"column":1}},"key":"DKeFHjNK5t"}],"key":"beb61sNDpz"}],"key":"pnS0toD7ZH"}],"key":"jFTSmBxjiL"},{"type":"heading","depth":2,"position":{"start":{"line":165,"column":1},"end":{"line":165,"column":1}},"children":[{"type":"text","value":"About Statistical Tests","position":{"start":{"line":165,"column":1},"end":{"line":165,"column":1}},"key":"mvYB4KEIBG"}],"identifier":"about-statistical-tests","label":"About Statistical Tests","html_id":"about-statistical-tests","implicit":true,"key":"P5KOSLwf7v"},{"type":"paragraph","position":{"start":{"line":167,"column":1},"end":{"line":167,"column":1}},"children":[{"type":"text","value":"There are so many tests. It is more important to know:","position":{"start":{"line":167,"column":1},"end":{"line":167,"column":1}},"key":"IQwzJk61XN"}],"key":"UJqzN5BsQ5"},{"type":"list","ordered":false,"spread":false,"position":{"start":{"line":168,"column":1},"end":{"line":179,"column":1}},"children":[{"type":"listItem","spread":true,"position":{"start":{"line":168,"column":1},"end":{"line":171,"column":1}},"children":[{"type":"paragraph","position":{"start":{"line":168,"column":1},"end":{"line":169,"column":1}},"children":[{"type":"text","value":"The key considerations for choosing a test:\nUnderstand the ","position":{"start":{"line":168,"column":1},"end":{"line":168,"column":1}},"key":"C26HztZlh6"},{"type":"emphasis","position":{"start":{"line":168,"column":1},"end":{"line":168,"column":1}},"children":[{"type":"text","value":"assumptions, requirements, and limitations of each test","position":{"start":{"line":168,"column":1},"end":{"line":168,"column":1}},"key":"wZMMrJ4jYf"}],"key":"viN1yAR65j"},{"type":"text","value":", as well as ","position":{"start":{"line":168,"column":1},"end":{"line":168,"column":1}},"key":"WNPjZgaHID"},{"type":"emphasis","position":{"start":{"line":168,"column":1},"end":{"line":168,"column":1}},"children":[{"type":"text","value":"the nature of your data","position":{"start":{"line":168,"column":1},"end":{"line":168,"column":1}},"key":"QsEJzLTDjr"}],"key":"pWg9TJPt0p"},{"type":"text","value":" and ","position":{"start":{"line":168,"column":1},"end":{"line":168,"column":1}},"key":"VApZp8VU5k"},{"type":"emphasis","position":{"start":{"line":168,"column":1},"end":{"line":168,"column":1}},"children":[{"type":"text","value":"research questions","position":{"start":{"line":168,"column":1},"end":{"line":168,"column":1}},"key":"BFmaeF04Rz"}],"key":"yEjr1zbSXf"},{"type":"text","value":", to select the most appropriate test.","position":{"start":{"line":168,"column":1},"end":{"line":168,"column":1}},"key":"JSrHo7MS8M"}],"key":"c6EHefkCqV"},{"type":"list","ordered":false,"spread":false,"position":{"start":{"line":170,"column":1},"end":{"line":171,"column":1}},"children":[{"type":"listItem","spread":true,"position":{"start":{"line":170,"column":1},"end":{"line":171,"column":1}},"children":[{"type":"paragraph","children":[{"type":"text","value":"Knowing these can help you to choose the appropriate test(s).","position":{"start":{"line":170,"column":1},"end":{"line":170,"column":1}},"key":"qPaTVRw2cq"}],"key":"tepRJUN45x"}],"key":"khi7DwUsmP"}],"key":"pkNZz9L1it"}],"key":"tKqBclqQuP"},{"type":"listItem","spread":true,"position":{"start":{"line":172,"column":1},"end":{"line":175,"column":1}},"children":[{"type":"paragraph","position":{"start":{"line":172,"column":1},"end":{"line":173,"column":1}},"children":[{"type":"text","value":"What you’re testing and why:\nBe clear to yourself about the null and alternative hypotheses, ","position":{"start":{"line":172,"column":1},"end":{"line":172,"column":1}},"key":"XNYihrsKSF"},{"type":"emphasis","position":{"start":{"line":172,"column":1},"end":{"line":172,"column":1}},"children":[{"type":"text","value":"the rationale behind them","position":{"start":{"line":172,"column":1},"end":{"line":172,"column":1}},"key":"HogrvISq4c"}],"key":"hDlTYlXIER"},{"type":"text","value":", and ","position":{"start":{"line":172,"column":1},"end":{"line":172,"column":1}},"key":"iVZBKs0Wuu"},{"type":"emphasis","position":{"start":{"line":172,"column":1},"end":{"line":172,"column":1}},"children":[{"type":"text","value":"the implications of your results","position":{"start":{"line":172,"column":1},"end":{"line":172,"column":1}},"key":"GBRi5dIDOH"}],"key":"fWFqhCVDcK"},{"type":"text","value":".","position":{"start":{"line":172,"column":1},"end":{"line":172,"column":1}},"key":"HTX0PAKfUC"}],"key":"EwLnOO9xYi"},{"type":"list","ordered":false,"spread":false,"position":{"start":{"line":174,"column":1},"end":{"line":175,"column":1}},"children":[{"type":"listItem","spread":true,"position":{"start":{"line":174,"column":1},"end":{"line":175,"column":1}},"children":[{"type":"paragraph","children":[{"type":"text","value":"Are you testing against CSR? Why?","position":{"start":{"line":174,"column":1},"end":{"line":174,"column":1}},"key":"e3tgyr67EW"}],"key":"Q8eQD4rxE9"}],"key":"mGkdxoYSQA"}],"key":"rEfB0xVT8Z"}],"key":"InQPtz3H39"},{"type":"listItem","spread":true,"position":{"start":{"line":176,"column":1},"end":{"line":179,"column":1}},"children":[{"type":"paragraph","position":{"start":{"line":176,"column":1},"end":{"line":177,"column":1}},"children":[{"type":"text","value":"Explicitly communicate your approach:\nyou have to explicitly tell your readers what, why, and how.","position":{"start":{"line":176,"column":1},"end":{"line":176,"column":1}},"key":"azxJ05i4kv"}],"key":"rUPUAKYwMf"},{"type":"list","ordered":false,"spread":false,"position":{"start":{"line":178,"column":1},"end":{"line":179,"column":1}},"children":[{"type":"listItem","spread":true,"position":{"start":{"line":178,"column":1},"end":{"line":179,"column":1}},"children":[{"type":"paragraph","children":[{"type":"text","value":"Don’t let your readers guess.","position":{"start":{"line":178,"column":1},"end":{"line":178,"column":1}},"key":"ZaJHhlc7Wf"}],"key":"rxUYEkY5qH"}],"key":"HchBShLAxf"}],"key":"vpdIkucZoh"}],"key":"CBIxbapNzk"}],"key":"Xhr6EYgYMB"},{"type":"paragraph","position":{"start":{"line":180,"column":1},"end":{"line":181,"column":1}},"children":[{"type":"emphasis","position":{"start":{"line":180,"column":1},"end":{"line":180,"column":1}},"children":[{"type":"text","value":"No single test is suitable for all situations, and it’s impossible to memorize every test.","position":{"start":{"line":180,"column":1},"end":{"line":180,"column":1}},"key":"EasmgKHyDp"}],"key":"pQ4DBIDKV4"},{"type":"text","value":"\nInstead, focus on developing a strong foundation in statistical concepts and ","position":{"start":{"line":180,"column":1},"end":{"line":180,"column":1}},"key":"PEoXpCAyvn"},{"type":"emphasis","position":{"start":{"line":180,"column":1},"end":{"line":180,"column":1}},"children":[{"type":"text","value":"knowing where to find","position":{"start":{"line":180,"column":1},"end":{"line":180,"column":1}},"key":"VIhKWF5cmt"}],"key":"N3DOcA8VmX"},{"type":"text","value":" relevant information when selecting the appropriate test for your specific needs.","position":{"start":{"line":180,"column":1},"end":{"line":180,"column":1}},"key":"PUOwZBi6SY"}],"key":"JjGqQLwQj4"},{"type":"heading","depth":3,"position":{"start":{"line":183,"column":1},"end":{"line":183,"column":1}},"children":[{"type":"text","value":"About p-value","position":{"start":{"line":183,"column":1},"end":{"line":183,"column":1}},"key":"oyAUvIvovn"}],"identifier":"about-p-value","label":"About p-value","html_id":"about-p-value","implicit":true,"key":"GlRjYO1fmP"},{"type":"list","ordered":false,"spread":false,"position":{"start":{"line":184,"column":1},"end":{"line":194,"column":1}},"children":[{"type":"listItem","spread":true,"position":{"start":{"line":184,"column":1},"end":{"line":185,"column":1}},"children":[{"type":"paragraph","position":{"start":{"line":184,"column":1},"end":{"line":184,"column":1}},"children":[{"type":"text","value":"p-value can only tell you how much risk you need to take if you reject H0.","position":{"start":{"line":184,"column":1},"end":{"line":184,"column":1}},"key":"IWH7OXith5"}],"key":"Yk7LrFWlFC"}],"key":"w9FybjrVw9"},{"type":"listItem","spread":true,"position":{"start":{"line":186,"column":1},"end":{"line":190,"column":1}},"children":[{"type":"paragraph","position":{"start":{"line":186,"column":1},"end":{"line":186,"column":1}},"children":[{"type":"text","value":"the common practice is to check if p-value ","position":{"start":{"line":186,"column":1},"end":{"line":186,"column":1}},"key":"YiXXJefoCZ"},{"type":"inlineMath","value":"< \\alpha","position":{"start":{"line":186,"column":1},"end":{"line":186,"column":1}},"html":"<span class=\"katex\"><span class=\"katex-mathml\"><math xmlns=\"http://www.w3.org/1998/Math/MathML\"><semantics><mrow><mo>&lt;</mo><mi>α</mi></mrow><annotation encoding=\"application/x-tex\">&lt; \\alpha</annotation></semantics></math></span><span class=\"katex-html\" aria-hidden=\"true\"><span class=\"base\"><span class=\"strut\" style=\"height:0.5782em;vertical-align:-0.0391em;\"></span><span class=\"mrel\">&lt;</span><span class=\"mspace\" style=\"margin-right:0.2778em;\"></span></span><span class=\"base\"><span class=\"strut\" style=\"height:0.4306em;\"></span><span class=\"mord mathnormal\" style=\"margin-right:0.0037em;\">α</span></span></span></span>","key":"IG4gdsWxZM"},{"type":"text","value":", and common alpha values are:","position":{"start":{"line":186,"column":1},"end":{"line":186,"column":1}},"key":"q4177JzaDW"}],"key":"VJm4S1UMzB"},{"type":"list","ordered":false,"spread":false,"position":{"start":{"line":187,"column":1},"end":{"line":190,"column":1}},"children":[{"type":"listItem","spread":true,"position":{"start":{"line":187,"column":1},"end":{"line":187,"column":1}},"children":[{"type":"paragraph","children":[{"type":"text","value":"0.05 for 95% confidence,","position":{"start":{"line":187,"column":1},"end":{"line":187,"column":1}},"key":"ysmDhIsEJH"}],"key":"dnhNzvu1uN"}],"key":"YENn5thLLl"},{"type":"listItem","spread":true,"position":{"start":{"line":188,"column":1},"end":{"line":188,"column":1}},"children":[{"type":"paragraph","children":[{"type":"text","value":"0.01 for 99% confidence, and","position":{"start":{"line":188,"column":1},"end":{"line":188,"column":1}},"key":"t2x9zRBO9H"}],"key":"n9086ersu7"}],"key":"NQIkmok1zi"},{"type":"listItem","spread":true,"position":{"start":{"line":189,"column":1},"end":{"line":190,"column":1}},"children":[{"type":"paragraph","children":[{"type":"text","value":"0.001 for 99.9% confidence.","position":{"start":{"line":189,"column":1},"end":{"line":189,"column":1}},"key":"tyNwLTSq6P"}],"key":"SGCLnWojRe"}],"key":"d5WMKkKnzi"}],"key":"AkJYnwCXDp"}],"key":"Sp3TWN2bRj"},{"type":"listItem","spread":true,"position":{"start":{"line":191,"column":1},"end":{"line":192,"column":1}},"children":[{"type":"paragraph","position":{"start":{"line":191,"column":1},"end":{"line":191,"column":1}},"children":[{"type":"text","value":"If p-value is less than the pre-determined ","position":{"start":{"line":191,"column":1},"end":{"line":191,"column":1}},"key":"rsCtft5AQc"},{"type":"inlineMath","value":"\\alpha","position":{"start":{"line":191,"column":1},"end":{"line":191,"column":1}},"html":"<span class=\"katex\"><span class=\"katex-mathml\"><math xmlns=\"http://www.w3.org/1998/Math/MathML\"><semantics><mrow><mi>α</mi></mrow><annotation encoding=\"application/x-tex\">\\alpha</annotation></semantics></math></span><span class=\"katex-html\" aria-hidden=\"true\"><span class=\"base\"><span class=\"strut\" style=\"height:0.4306em;\"></span><span class=\"mord mathnormal\" style=\"margin-right:0.0037em;\">α</span></span></span></span>","key":"Evfb11BY0i"},{"type":"text","value":", then it is significantly different.","position":{"start":{"line":191,"column":1},"end":{"line":191,"column":1}},"key":"wrcCKjLoXB"}],"key":"QhAq4AifQt"}],"key":"boIDVtJqGL"},{"type":"listItem","spread":true,"position":{"start":{"line":193,"column":1},"end":{"line":194,"column":1}},"children":[{"type":"paragraph","position":{"start":{"line":193,"column":1},"end":{"line":193,"column":1}},"children":[{"type":"text","value":"That’s how far you can get with p-value---","position":{"start":{"line":193,"column":1},"end":{"line":193,"column":1}},"key":"HFRmJB5ucy"},{"type":"strong","position":{"start":{"line":193,"column":1},"end":{"line":193,"column":1}},"children":[{"type":"text","value":"don’t over-interpret the p-value","position":{"start":{"line":193,"column":1},"end":{"line":193,"column":1}},"key":"mSk078cUBm"}],"key":"BTXU6Jsa69"},{"type":"text","value":".","position":{"start":{"line":193,"column":1},"end":{"line":193,"column":1}},"key":"hmGvSL1l9Y"}],"key":"LgKJS9MpUc"},{"type":"list","ordered":false,"spread":false,"position":{"start":{"line":194,"column":1},"end":{"line":194,"column":1}},"children":[{"type":"listItem","spread":true,"position":{"start":{"line":194,"column":1},"end":{"line":194,"column":1}},"children":[{"type":"paragraph","children":[{"type":"text","value":"Comparing p-values can be problematic, because they may be calculated from different settings, e.g., sample size.","position":{"start":{"line":194,"column":1},"end":{"line":194,"column":1}},"key":"rbBlKDZjCU"}],"key":"DUyLKTQhZg"}],"key":"xu1RMBH5NR"}],"key":"AafU98aZI8"}],"key":"GKHWxP1lss"}],"key":"x4Rsy4d1Qp"}],"key":"EKv728MN52"}],"key":"dqUKtcNy0T"},"references":{"cite":{"order":["Goreaud_1999"],"data":{"Goreaud_1999":{"label":"Goreaud_1999","enumerator":"1","doi":"10.2307/3237072","html":"Goreaud, F., & Pélissier, R. (1999). On explicit formulas of edge effect correction for Ripley’sK‐function. <i>Journal of Vegetation Science</i>, <i>10</i>(3), 433–438. <a target=\"_blank\" rel=\"noreferrer\" href=\"https://doi.org/10.2307/3237072\">10.2307/3237072</a>","url":"https://doi.org/10.2307/3237072"}}}}}