{"version":2,"kind":"Article","sha256":"fad7cce164105f8a71bd3b58b3f58ec089281a4be64d174cf47406613d7df2f5","slug":"sec-06-02","location":"/src/content/sec_06-02.md","dependencies":[],"frontmatter":{"title":"Key Components of Maps","content_includes_title":false,"authors":[{"nameParsed":{"literal":"Benny Chin","given":"Benny","family":"Chin"},"name":"Benny Chin","affiliations":["GIS Unit, Geography, National University of Singapore"],"id":"contributors-myst-generated-uid-0"}],"license":{"content":{"id":"CC-BY-NC-SA-4.0","url":"https://creativecommons.org/licenses/by-nc-sa/4.0/","name":"Creative Commons Attribution Non Commercial Share Alike 4.0 International","CC":true},"code":{"id":"MIT-0","url":"https://opensource.org/licenses/MIT-0","name":"MIT No Attribution","osi":true}},"github":"https://github.com/wcchin/geo-stat-vis","keywords":["GIS","GIScience","Cartography","Spatial Analysis"],"copyright":"2025 National University of Singapore","affiliations":[{"id":"GIS Unit, Geography, National University of Singapore","name":"GIS Unit, Geography, National University of Singapore"}],"numbering":{"title":{"offset":1}},"thumbnail":"/drawing_sizes_1a-1696741095e529bf30c7fca847bcf022.png","exports":[{"format":"md","filename":"sec_06-02.md","url":"/sec_06-02-3351c2e83b56c64f18c63ddc0d1c5f82.md"}]},"mdast":{"type":"root","children":[{"type":"block","children":[{"type":"list","ordered":false,"spread":false,"position":{"start":{"line":3,"column":1},"end":{"line":9,"column":1}},"children":[{"type":"listItem","spread":true,"position":{"start":{"line":3,"column":1},"end":{"line":3,"column":1}},"children":[{"type":"paragraph","children":[{"type":"text","value":"Sizes","position":{"start":{"line":3,"column":1},"end":{"line":3,"column":1}},"key":"fCEqdHWkpP"}],"key":"Bb1bs0cFcE"}],"key":"Js2WejGQiT"},{"type":"listItem","spread":true,"position":{"start":{"line":4,"column":1},"end":{"line":4,"column":1}},"children":[{"type":"paragraph","children":[{"type":"text","value":"Typography","position":{"start":{"line":4,"column":1},"end":{"line":4,"column":1}},"key":"F42U7ATaIG"}],"key":"svxs6LLzg9"}],"key":"T4jsVQV0Zj"},{"type":"listItem","spread":true,"position":{"start":{"line":5,"column":1},"end":{"line":5,"column":1}},"children":[{"type":"paragraph","children":[{"type":"text","value":"Colors","position":{"start":{"line":5,"column":1},"end":{"line":5,"column":1}},"key":"cy7BANXjbL"}],"key":"pkutxQzJWS"}],"key":"A7WXII5QEE"},{"type":"listItem","spread":true,"position":{"start":{"line":6,"column":1},"end":{"line":6,"column":1}},"children":[{"type":"paragraph","children":[{"type":"text","value":"Coordinate System","position":{"start":{"line":6,"column":1},"end":{"line":6,"column":1}},"key":"xlCNr1ICwv"}],"key":"ZYupXcrRk8"}],"key":"iqRAthBHw3"},{"type":"listItem","spread":true,"position":{"start":{"line":7,"column":1},"end":{"line":9,"column":1}},"children":[{"type":"paragraph","children":[{"type":"text","value":"Arrangement","position":{"start":{"line":7,"column":1},"end":{"line":7,"column":1}},"key":"oHBiNVn5Vf"}],"key":"bYwl3DwbEL"}],"key":"hMB557SSDe"}],"key":"PRCPNcXu0G"},{"type":"heading","depth":2,"position":{"start":{"line":10,"column":1},"end":{"line":10,"column":1}},"children":[{"type":"text","value":"Sizes","position":{"start":{"line":10,"column":1},"end":{"line":10,"column":1}},"key":"oIqO7leVeL"}],"identifier":"sizes","label":"Sizes","html_id":"sizes","implicit":true,"key":"OIZuunCIYs"},{"type":"paragraph","position":{"start":{"line":11,"column":1},"end":{"line":11,"column":1}},"children":[{"type":"text","value":"The size of the map:","position":{"start":{"line":11,"column":1},"end":{"line":11,"column":1}},"key":"BwnroKau4i"}],"key":"lMlV6WR4G5"},{"type":"list","ordered":false,"spread":false,"position":{"start":{"line":12,"column":1},"end":{"line":18,"column":1}},"children":[{"type":"listItem","spread":true,"position":{"start":{"line":12,"column":1},"end":{"line":12,"column":1}},"children":[{"type":"paragraph","children":[{"type":"text","value":"a ‘full’ width figure in an A4 paper (e.g., thesis, reports)","position":{"start":{"line":12,"column":1},"end":{"line":12,"column":1}},"key":"E303qU8Qbv"}],"key":"mcfb76pqy3"}],"key":"Vn3O4lzkNI"},{"type":"listItem","spread":true,"position":{"start":{"line":13,"column":1},"end":{"line":14,"column":1}},"children":[{"type":"paragraph","children":[{"type":"text","value":"a ‘half’ width figure in an A4 paper","position":{"start":{"line":13,"column":1},"end":{"line":13,"column":1}},"key":"GDzrUXQ4JT"},{"type":"break","position":{"start":{"line":13,"column":1},"end":{"line":13,"column":1}},"key":"AMBQeDhNwA"},{"type":"text","value":"(i.e., to fit in one column of a two columns layout)","position":{"start":{"line":13,"column":1},"end":{"line":13,"column":1}},"key":"ktk9qq5I3t"}],"key":"txqvPynsrr"}],"key":"nPM1fBb1OM"},{"type":"listItem","spread":true,"position":{"start":{"line":15,"column":1},"end":{"line":15,"column":1}},"children":[{"type":"paragraph","children":[{"type":"text","value":"as one of the element inside an A1 poster","position":{"start":{"line":15,"column":1},"end":{"line":15,"column":1}},"key":"lFr0Kg1mLt"}],"key":"CiqmaqphYW"}],"key":"bouSP9yqXk"},{"type":"listItem","spread":true,"position":{"start":{"line":16,"column":1},"end":{"line":16,"column":1}},"children":[{"type":"paragraph","children":[{"type":"text","value":"a full A0 poster-size map","position":{"start":{"line":16,"column":1},"end":{"line":16,"column":1}},"key":"qWBUpf0N7w"}],"key":"bDRSlWWwcI"}],"key":"xoOcwigXjL"},{"type":"listItem","spread":true,"position":{"start":{"line":17,"column":1},"end":{"line":18,"column":1}},"children":[{"type":"paragraph","children":[{"type":"text","value":"in a Powerpoint slide (full-page vs. as an element)","position":{"start":{"line":17,"column":1},"end":{"line":17,"column":1}},"key":"ZmlfOoEhXf"}],"key":"XYgH0JscwN"}],"key":"hD8u3MUrer"}],"key":"BOEjoeib5h"},{"type":"paragraph","position":{"start":{"line":19,"column":1},"end":{"line":20,"column":1}},"children":[{"type":"strong","position":{"start":{"line":19,"column":1},"end":{"line":19,"column":1}},"children":[{"type":"text","value":"Map details","position":{"start":{"line":19,"column":1},"end":{"line":19,"column":1}},"key":"ErOOgPZoZw"}],"key":"ZWFAjxH4m1"},{"type":"text","value":"\nHow much detail can be shown in:","position":{"start":{"line":19,"column":1},"end":{"line":19,"column":1}},"key":"cyEI4W9HPM"}],"key":"hAMu8L0DZy"},{"type":"list","ordered":false,"spread":false,"position":{"start":{"line":21,"column":1},"end":{"line":23,"column":1}},"children":[{"type":"listItem","spread":true,"position":{"start":{"line":21,"column":1},"end":{"line":21,"column":1}},"children":[{"type":"paragraph","children":[{"type":"text","value":"a small A4-one-column map","position":{"start":{"line":21,"column":1},"end":{"line":21,"column":1}},"key":"a075U2m43L"}],"key":"ofj6Vk8i7l"}],"key":"fO0qtIRBYr"},{"type":"listItem","spread":true,"position":{"start":{"line":22,"column":1},"end":{"line":23,"column":1}},"children":[{"type":"paragraph","children":[{"type":"text","value":"a full A0 poster-size map","position":{"start":{"line":22,"column":1},"end":{"line":22,"column":1}},"key":"Bf2KnrEpzB"}],"key":"OeGk7vNR8O"}],"key":"r5RVCKXgE9"}],"key":"kDKDVimxLg"},{"type":"paragraph","position":{"start":{"line":24,"column":1},"end":{"line":24,"column":1}},"children":[{"type":"text","value":"Two thinking directions:","position":{"start":{"line":24,"column":1},"end":{"line":24,"column":1}},"key":"E0lTbma2Dh"}],"key":"S6VhG6qvV7"},{"type":"list","ordered":false,"spread":false,"position":{"start":{"line":25,"column":1},"end":{"line":28,"column":1}},"children":[{"type":"listItem","spread":true,"position":{"start":{"line":25,"column":1},"end":{"line":25,"column":1}},"children":[{"type":"paragraph","children":[{"type":"text","value":"What should be added --- the ‘plus’","position":{"start":{"line":25,"column":1},"end":{"line":25,"column":1}},"key":"bNGUSuWvCl"}],"key":"Lcha3LmhZ3"}],"key":"jbOX7i4lEB"},{"type":"listItem","spread":true,"position":{"start":{"line":26,"column":1},"end":{"line":28,"column":1}},"children":[{"type":"paragraph","children":[{"type":"text","value":"What should be removed --- the ‘minus’","position":{"start":{"line":26,"column":1},"end":{"line":26,"column":1}},"key":"Y1Vrw1PTGt"}],"key":"segj2ARVuo"}],"key":"iK8dFg9RMX"}],"key":"TOSTsf1tSk"},{"type":"paragraph","position":{"start":{"line":29,"column":1},"end":{"line":30,"column":1}},"children":[{"type":"strong","position":{"start":{"line":29,"column":1},"end":{"line":29,"column":1}},"children":[{"type":"text","value":"DPI","position":{"start":{"line":29,"column":1},"end":{"line":29,"column":1}},"key":"R1iLOiNZQy"}],"key":"sonbCPVQES"},{"type":"break","position":{"start":{"line":29,"column":1},"end":{"line":29,"column":1}},"key":"P7AGkwhMf6"},{"type":"text","value":"(dots-per-inch): the number of dots that will be drawn or printed within a one-inch span (in a single dimension).","position":{"start":{"line":29,"column":1},"end":{"line":29,"column":1}},"key":"h0D3cujapF"}],"key":"eG8yfHEx5a"},{"type":"paragraph","position":{"start":{"line":32,"column":1},"end":{"line":32,"column":1}},"children":[{"type":"strong","position":{"start":{"line":32,"column":1},"end":{"line":32,"column":1}},"children":[{"type":"text","value":"Think:","position":{"start":{"line":32,"column":1},"end":{"line":32,"column":1}},"key":"ddmXbuVlAb"}],"key":"kcqnXM3Foy"}],"key":"LvXOrVMCtP"},{"type":"list","ordered":false,"spread":false,"position":{"start":{"line":33,"column":1},"end":{"line":35,"column":1}},"children":[{"type":"listItem","spread":true,"position":{"start":{"line":33,"column":1},"end":{"line":33,"column":1}},"children":[{"type":"paragraph","children":[{"type":"text","value":"What happens when you put an A0-size map/image inside an A4 paper?","position":{"start":{"line":33,"column":1},"end":{"line":33,"column":1}},"key":"eW505Aqsiw"}],"key":"hedwBECegP"}],"key":"we3BlLGrRQ"},{"type":"listItem","spread":true,"position":{"start":{"line":34,"column":1},"end":{"line":35,"column":1}},"children":[{"type":"paragraph","children":[{"type":"text","value":"How does a 2cm line in the original A0 map look on the A4 paper?","position":{"start":{"line":34,"column":1},"end":{"line":34,"column":1}},"key":"WlRMkHY4C0"}],"key":"OUneEG98Y6"}],"key":"hg23N5YUiG"}],"key":"r1uo3JNZEn"},{"type":"paragraph","position":{"start":{"line":36,"column":1},"end":{"line":37,"column":1}},"children":[{"type":"strong","position":{"start":{"line":36,"column":1},"end":{"line":36,"column":1}},"children":[{"type":"text","value":"Take home message","position":{"start":{"line":36,"column":1},"end":{"line":36,"column":1}},"key":"x8bUQWavma"}],"key":"NTupB25eBi"},{"type":"text","value":":","position":{"start":{"line":36,"column":1},"end":{"line":36,"column":1}},"key":"jTqHFL7KZ1"},{"type":"break","position":{"start":{"line":36,"column":1},"end":{"line":36,"column":1}},"key":"YERNoa0X7e"},{"type":"text","value":"Always plan ahead about what size of map to be drawn.","position":{"start":{"line":36,"column":1},"end":{"line":36,"column":1}},"key":"GhONQlfnK5"}],"key":"gC0X42X7KJ"},{"type":"container","kind":"figure","children":[{"type":"image","url":"/drawing_sizes_1a-1696741095e529bf30c7fca847bcf022.png","alt":"difference size","align":"center","key":"LB7tnv8Qxm","urlSource":"./resources/w01-img/drawing_sizes_1a.png"},{"type":"caption","children":[{"type":"paragraph","position":{"start":{"line":44,"column":1},"end":{"line":44,"column":1}},"children":[{"type":"captionNumber","kind":"figure","label":"effectofsize","identifier":"effectofsize","html_id":"effectofsize","enumerator":"1","children":[{"type":"text","value":"Figure ","key":"oxKnHOfgzc"},{"type":"text","value":"1","key":"gmYxotHzgL"},{"type":"text","value":":","key":"CQQHuWQOxU"}],"template":"Figure %s:","key":"Zm1q4a0knk"},{"type":"text","value":"The same map export with different size, squeezed to the same display size.","position":{"start":{"line":44,"column":1},"end":{"line":44,"column":1}},"key":"k6pShsepSV"}],"key":"hVyKGwbTR1"}],"key":"wNJjrTG9CG"}],"label":"effectofsize","identifier":"effectofsize","enumerator":"1","html_id":"effectofsize","key":"Ia7lpxOkdR"},{"type":"container","kind":"figure","children":[{"type":"image","url":"/drawing_sizes_1b-71feb03dd81c6aa27bcec9729a851493.png","alt":"zoom in","align":"center","key":"zESJ9w9uU2","urlSource":"./resources/w01-img/drawing_sizes_1b.png"},{"type":"caption","children":[{"type":"paragraph","position":{"start":{"line":52,"column":1},"end":{"line":52,"column":1}},"children":[{"type":"captionNumber","kind":"figure","label":"zoomin","identifier":"zoomin","html_id":"zoomin","enumerator":"2","children":[{"type":"text","value":"Figure ","key":"efxMQNYSIb"},{"type":"text","value":"2","key":"MMx2yyJWeK"},{"type":"text","value":":","key":"NHgKciQDFa"}],"template":"Figure %s:","key":"YnRDUM8aff"},{"type":"text","value":"The same 4 maps, zoomed-in.","position":{"start":{"line":52,"column":1},"end":{"line":52,"column":1}},"key":"FURGQvSNDH"}],"key":"K3REIHLdIc"}],"key":"xgBywQPu0H"}],"label":"zoomin","identifier":"zoomin","enumerator":"2","html_id":"zoomin","key":"KS5xZqVOVe"},{"type":"heading","depth":2,"position":{"start":{"line":56,"column":1},"end":{"line":56,"column":1}},"children":[{"type":"text","value":"Typography","position":{"start":{"line":56,"column":1},"end":{"line":56,"column":1}},"key":"IxHlEAfIqA"}],"identifier":"typography","label":"Typography","html_id":"typography","implicit":true,"key":"wkD3aKfFqv"},{"type":"paragraph","position":{"start":{"line":58,"column":1},"end":{"line":59,"column":1}},"children":[{"type":"text","value":"Typography most often serves to label cartographic elements.\nIt is a ","position":{"start":{"line":58,"column":1},"end":{"line":58,"column":1}},"key":"ejMO0UjiLu"},{"type":"strong","position":{"start":{"line":58,"column":1},"end":{"line":58,"column":1}},"children":[{"type":"text","value":"“functional symbol”","position":{"start":{"line":58,"column":1},"end":{"line":58,"column":1}},"key":"G5aFdGYouf"}],"key":"awxponXGNt"},{"type":"text","value":" primarily, and secondarily an ","position":{"start":{"line":58,"column":1},"end":{"line":58,"column":1}},"key":"WP1azAEiNw"},{"type":"strong","position":{"start":{"line":58,"column":1},"end":{"line":58,"column":1}},"children":[{"type":"text","value":"aesthetic element​","position":{"start":{"line":58,"column":1},"end":{"line":58,"column":1}},"key":"CFvUlt3uWA"}],"key":"CZsAQT3xAN"},{"type":"text","value":" meaning that ","position":{"start":{"line":58,"column":1},"end":{"line":58,"column":1}},"key":"kWoBxD9FxZ"},{"type":"strong","position":{"start":{"line":58,"column":1},"end":{"line":58,"column":1}},"children":[{"type":"text","value":"it carries cartographic meaning​","position":{"start":{"line":58,"column":1},"end":{"line":58,"column":1}},"key":"LOMUnUcYCc"}],"key":"AlBn8sAVnc"},{"type":"text","value":" and ","position":{"start":{"line":58,"column":1},"end":{"line":58,"column":1}},"key":"c4WeQTUohu"},{"type":"strong","position":{"start":{"line":58,"column":1},"end":{"line":58,"column":1}},"children":[{"type":"text","value":"is not simply “window dressing”","position":{"start":{"line":58,"column":1},"end":{"line":58,"column":1}},"key":"ji4rCgKJUf"}],"key":"dO3y0OzKdI"},{"type":"text","value":".","position":{"start":{"line":58,"column":1},"end":{"line":58,"column":1}},"key":"c53DtEWC2S"}],"key":"n8Uvv7mKCW"},{"type":"aside","children":[{"type":"admonitionTitle","children":[{"type":"text","value":"About Typography","position":{"start":{"line":61,"column":1},"end":{"line":61,"column":1}},"key":"F3GUqcMZTF"}],"key":"IrpII1Hmyu"},{"type":"paragraph","position":{"start":{"line":62,"column":1},"end":{"line":62,"column":1}},"children":[{"type":"link","url":"https://colorado.pressbooks.pub/makingmaps/chapter/typography/","position":{"start":{"line":62,"column":1},"end":{"line":62,"column":1}},"children":[{"type":"text","value":"Typography, from Making Effective Maps: Cartographic Visualization for GIS","position":{"start":{"line":62,"column":1},"end":{"line":62,"column":1}},"key":"TZYf30fW4U"}],"urlSource":"https://colorado.pressbooks.pub/makingmaps/chapter/typography/","key":"sJYSWDjTqN"}],"key":"HGgt9PfrUt"}],"key":"HWZZIwZru6"},{"type":"list","ordered":false,"spread":false,"position":{"start":{"line":65,"column":1},"end":{"line":70,"column":1}},"children":[{"type":"listItem","spread":true,"position":{"start":{"line":65,"column":1},"end":{"line":65,"column":1}},"children":[{"type":"paragraph","children":[{"type":"text","value":"Font Family (Serif, Sans-Serif, Decorative, Monospaced)","position":{"start":{"line":65,"column":1},"end":{"line":65,"column":1}},"key":"XvSLxAifVW"}],"key":"JerIcUMcEe"}],"key":"IRhhu7txPX"},{"type":"listItem","spread":true,"position":{"start":{"line":66,"column":1},"end":{"line":66,"column":1}},"children":[{"type":"paragraph","children":[{"type":"text","value":"Font Size (relative to map size)","position":{"start":{"line":66,"column":1},"end":{"line":66,"column":1}},"key":"uXo0GrLTaM"}],"key":"FXPTAhIQQ0"}],"key":"VYRG0oPKdI"},{"type":"listItem","spread":true,"position":{"start":{"line":67,"column":1},"end":{"line":67,"column":1}},"children":[{"type":"paragraph","children":[{"type":"text","value":"Font Weight (Bold (700) vs. Regular (400) vs. Light (300))","position":{"start":{"line":67,"column":1},"end":{"line":67,"column":1}},"key":"dyQurcpbs1"}],"key":"zY73xVZqjF"}],"key":"K0Sarem43E"},{"type":"listItem","spread":true,"position":{"start":{"line":68,"column":1},"end":{"line":68,"column":1}},"children":[{"type":"paragraph","children":[{"type":"text","value":"Font style (italic vs. regular)","position":{"start":{"line":68,"column":1},"end":{"line":68,"column":1}},"key":"egVGwuRyUA"}],"key":"cT2Ow26U5n"}],"key":"rPXsvpHtUN"},{"type":"listItem","spread":true,"position":{"start":{"line":69,"column":1},"end":{"line":70,"column":1}},"children":[{"type":"paragraph","children":[{"type":"text","value":"Uppercase, lowercase, title case","position":{"start":{"line":69,"column":1},"end":{"line":69,"column":1}},"key":"r45QYa8aUi"}],"key":"ue6APLo2GF"}],"key":"ha7owuhHJS"}],"key":"nabjIxT4qm"},{"type":"paragraph","position":{"start":{"line":71,"column":1},"end":{"line":71,"column":1}},"children":[{"type":"emphasis","position":{"start":{"line":71,"column":1},"end":{"line":71,"column":1}},"children":[{"type":"text","value":"What is the differences between Sans Serif fonts and Serif fonts?","position":{"start":{"line":71,"column":1},"end":{"line":71,"column":1}},"key":"HEyPeLBjFd"}],"key":"Fh6H5eq3dM"}],"key":"jkpFJ7gtJP"},{"type":"container","kind":"figure","children":[{"type":"image","url":"/drawing-fonts-d4551ae23a12284c681ec127d25e11f6.png","alt":"san-serif and serif","align":"center","key":"O50NmgqROk","urlSource":"./resources/w01-img/drawing-fonts.png"},{"type":"caption","children":[{"type":"paragraph","position":{"start":{"line":78,"column":1},"end":{"line":78,"column":1}},"children":[{"type":"captionNumber","kind":"figure","label":"fonts","identifier":"fonts","html_id":"fonts","enumerator":"3","children":[{"type":"text","value":"Figure ","key":"QO1zPmIuuX"},{"type":"text","value":"3","key":"FbrnadeBz9"},{"type":"text","value":":","key":"nw4hnxxsbo"}],"template":"Figure %s:","key":"QAmt1wEx5b"},{"type":"text","value":"Some example of Sans-Serif fonts (left) and Serif fonts (right).","position":{"start":{"line":78,"column":1},"end":{"line":78,"column":1}},"key":"jMK77OZLEd"}],"key":"cdZquMp0Te"}],"key":"Kp65zRzDO3"}],"label":"fonts","identifier":"fonts","enumerator":"3","html_id":"fonts","key":"zYOZ3ClfpH"},{"type":"container","kind":"figure","children":[{"type":"image","url":"/text_elements-1636a3582813f39e2fbbd91504c46bc4.png","alt":"text element","align":"center","key":"YleZzsilG2","urlSource":"./resources/w01-img/text_elements.png"},{"type":"caption","children":[{"type":"paragraph","position":{"start":{"line":86,"column":1},"end":{"line":86,"column":1}},"children":[{"type":"captionNumber","kind":"figure","label":"textele","identifier":"textele","html_id":"textele","enumerator":"4","children":[{"type":"text","value":"Figure ","key":"MavwY01hQd"},{"type":"text","value":"4","key":"IDTifsAa06"},{"type":"text","value":":","key":"hGCZ8KZu3m"}],"template":"Figure %s:","key":"lwuASqlwr8"},{"type":"text","value":"Text elements.","position":{"start":{"line":86,"column":1},"end":{"line":86,"column":1}},"key":"HYhFbQWsaT"}],"key":"nViKfHhUrw"}],"key":"BIC7uEGYj9"}],"label":"textele","identifier":"textele","enumerator":"4","html_id":"textele","key":"SjFRAdXcjR"},{"type":"paragraph","position":{"start":{"line":90,"column":1},"end":{"line":90,"column":1}},"children":[{"type":"text","value":"Things to be considered:","position":{"start":{"line":90,"column":1},"end":{"line":90,"column":1}},"key":"GSmLsP8hn0"}],"key":"QuMuXHJ2jX"},{"type":"list","ordered":false,"spread":false,"position":{"start":{"line":91,"column":1},"end":{"line":96,"column":1}},"children":[{"type":"listItem","spread":true,"position":{"start":{"line":91,"column":1},"end":{"line":91,"column":1}},"children":[{"type":"paragraph","children":[{"type":"strong","position":{"start":{"line":91,"column":1},"end":{"line":91,"column":1}},"children":[{"type":"text","value":"Visibility","position":{"start":{"line":91,"column":1},"end":{"line":91,"column":1}},"key":"l2b65W7WdI"}],"key":"pMIvCI04jM"},{"type":"text","value":": make sure the labels can be viewed without zoom-in.","position":{"start":{"line":91,"column":1},"end":{"line":91,"column":1}},"key":"ouWggSduTD"}],"key":"wcwL7wkN2L"}],"key":"jjXxWfSRNp"},{"type":"listItem","spread":true,"position":{"start":{"line":92,"column":1},"end":{"line":92,"column":1}},"children":[{"type":"paragraph","children":[{"type":"strong","position":{"start":{"line":92,"column":1},"end":{"line":92,"column":1}},"children":[{"type":"text","value":"Hierarchy","position":{"start":{"line":92,"column":1},"end":{"line":92,"column":1}},"key":"UJiXG6a6sv"}],"key":"biCNMPFE0R"},{"type":"text","value":": use different sizes, weights, or styles to show hierarchy of labels.","position":{"start":{"line":92,"column":1},"end":{"line":92,"column":1}},"key":"HRszR36kWD"}],"key":"dQQn8Pt1R4"}],"key":"VLM6sKRtmp"},{"type":"listItem","spread":true,"position":{"start":{"line":93,"column":1},"end":{"line":93,"column":1}},"children":[{"type":"paragraph","children":[{"type":"strong","position":{"start":{"line":93,"column":1},"end":{"line":93,"column":1}},"children":[{"type":"text","value":"Consistency","position":{"start":{"line":93,"column":1},"end":{"line":93,"column":1}},"key":"x467zNFnP3"}],"key":"uFzUuDPg07"},{"type":"text","value":": use the same typeface to show labels in the same level.","position":{"start":{"line":93,"column":1},"end":{"line":93,"column":1}},"key":"FZmw07pgSV"}],"key":"pwbUsYz4TL"}],"key":"qEHnjZ0m5A"},{"type":"listItem","spread":true,"position":{"start":{"line":94,"column":1},"end":{"line":94,"column":1}},"children":[{"type":"paragraph","children":[{"type":"strong","position":{"start":{"line":94,"column":1},"end":{"line":94,"column":1}},"children":[{"type":"text","value":"License","position":{"start":{"line":94,"column":1},"end":{"line":94,"column":1}},"key":"wxZiYzW9fM"}],"key":"aJsDvJMxqi"},{"type":"text","value":": make sure the font can be used in your targeted publication or is there any restriction/subscription-needed","position":{"start":{"line":94,"column":1},"end":{"line":94,"column":1}},"key":"Wf6zACW4zr"}],"key":"n7yyiCqBVN"}],"key":"CEf4dsaPxj"},{"type":"listItem","spread":true,"position":{"start":{"line":95,"column":1},"end":{"line":96,"column":1}},"children":[{"type":"paragraph","children":[{"type":"strong","position":{"start":{"line":95,"column":1},"end":{"line":95,"column":1}},"children":[{"type":"text","value":"Publication requirement","position":{"start":{"line":95,"column":1},"end":{"line":95,"column":1}},"key":"RhBbuyznE6"}],"key":"YrbWTu39GP"},{"type":"text","value":": some journal requested that some specific fonts should be used for some of the map elements.","position":{"start":{"line":95,"column":1},"end":{"line":95,"column":1}},"key":"wPpbXRdhhO"}],"key":"soGa9rvh6W"}],"key":"Hc45JphXMz"}],"key":"teHiKNoPF0"},{"type":"paragraph","position":{"start":{"line":97,"column":1},"end":{"line":98,"column":1}},"children":[{"type":"strong","position":{"start":{"line":97,"column":1},"end":{"line":97,"column":1}},"children":[{"type":"text","value":"Take home message","position":{"start":{"line":97,"column":1},"end":{"line":97,"column":1}},"key":"zePavxVhlE"}],"key":"jX9Ga63zrk"},{"type":"text","value":":\nThe top priority is to ensure that the text is ","position":{"start":{"line":97,"column":1},"end":{"line":97,"column":1}},"key":"qcPpJsW0GC"},{"type":"emphasis","position":{"start":{"line":97,"column":1},"end":{"line":97,"column":1}},"children":[{"type":"text","value":"clear and readable","position":{"start":{"line":97,"column":1},"end":{"line":97,"column":1}},"key":"YFUmWUMIl7"}],"key":"wV5f73w4kj"},{"type":"text","value":". Additionally, make sure the fonts are appropriate for your target venue.","position":{"start":{"line":97,"column":1},"end":{"line":97,"column":1}},"key":"QVB8jTjfVo"}],"key":"AWj3e4QDEc"},{"type":"heading","depth":2,"position":{"start":{"line":100,"column":1},"end":{"line":100,"column":1}},"children":[{"type":"text","value":"Colours","position":{"start":{"line":100,"column":1},"end":{"line":100,"column":1}},"key":"XvGxnxShri"}],"identifier":"colours","label":"Colours","html_id":"colours","implicit":true,"key":"vO62v03vwj"},{"type":"paragraph","position":{"start":{"line":102,"column":1},"end":{"line":102,"column":1}},"children":[{"type":"text","value":"In the realm of cartography and geovisualization, color is an essential tool that serves to delineate different components and highlight their significance, thereby facilitating effective visual communication. In designing geovisualization, ","position":{"start":{"line":102,"column":1},"end":{"line":102,"column":1}},"key":"v9cVRhsxWy"},{"type":"emphasis","position":{"start":{"line":102,"column":1},"end":{"line":102,"column":1}},"children":[{"type":"text","value":"the application of color goes beyond aesthetics, as it enables the clear differentiation of features and allows for the accurate representation of data","position":{"start":{"line":102,"column":1},"end":{"line":102,"column":1}},"key":"VOL2OIGoUA"}],"key":"D7Kgsb3ElC"},{"type":"text","value":", making it a crucial aspect of geovisualization design.","position":{"start":{"line":102,"column":1},"end":{"line":102,"column":1}},"key":"uEUsX3rDKP"}],"key":"JbxlLHIK0R"},{"type":"container","kind":"figure","children":[{"type":"image","url":"/US_temperature_map-55acabe5a4a9e4f034b9caacacec9980.png","alt":"Temperature of colors. Source: NASA Earth Observatory: Arctic Chill Sweeps U.S.","align":"center","data":{"altTextIsAutoGenerated":true},"key":"LurAZi8FC0","urlSource":"./resources/w01-img/US_temperature_map.png"},{"type":"caption","children":[{"type":"paragraph","position":{"start":{"line":109,"column":1},"end":{"line":109,"column":1}},"children":[{"type":"text","value":"Temperature of colors. Source: NASA Earth Observatory: ","position":{"start":{"line":109,"column":1},"end":{"line":109,"column":1}},"key":"NEvov9ASyp"},{"type":"link","url":"https://earthobservatory.nasa.gov/images/152333/arctic-chill-sweeps-us","position":{"start":{"line":109,"column":1},"end":{"line":109,"column":1}},"children":[{"type":"text","value":"Arctic Chill Sweeps U.S.","position":{"start":{"line":109,"column":1},"end":{"line":109,"column":1}},"key":"VZHT6B0ArA"}],"urlSource":"https://earthobservatory.nasa.gov/images/152333/arctic-chill-sweeps-us","key":"QqGhyO7SqF"}],"key":"wUeUh26KK0"}],"key":"GHWyK1NYNN"}],"enumerator":"5","key":"eGbAOH7Lay"},{"type":"paragraph","position":{"start":{"line":113,"column":1},"end":{"line":113,"column":1}},"children":[{"type":"text","value":"Things to considered while selecting color(s):","position":{"start":{"line":113,"column":1},"end":{"line":113,"column":1}},"key":"o9RhhoNBzu"}],"key":"iqRqug8JtH"},{"type":"list","ordered":false,"spread":false,"position":{"start":{"line":114,"column":1},"end":{"line":134,"column":1}},"children":[{"type":"listItem","spread":true,"position":{"start":{"line":114,"column":1},"end":{"line":115,"column":1}},"children":[{"type":"paragraph","position":{"start":{"line":114,"column":1},"end":{"line":114,"column":1}},"children":[{"type":"text","value":"The targeted  audiences or venues: color or black and white (and grey)?, colorblind? etc....","position":{"start":{"line":114,"column":1},"end":{"line":114,"column":1}},"key":"SrrID0VBUH"}],"key":"UzYzgUMrUF"}],"key":"Sjbbg4RXMA"},{"type":"listItem","spread":true,"position":{"start":{"line":116,"column":1},"end":{"line":124,"column":1}},"children":[{"type":"paragraph","position":{"start":{"line":116,"column":1},"end":{"line":116,"column":1}},"children":[{"type":"text","value":"Types of values:","position":{"start":{"line":116,"column":1},"end":{"line":116,"column":1}},"key":"It1dAvaqjh"}],"key":"Tn8narf9Hl"},{"type":"list","ordered":false,"spread":false,"position":{"start":{"line":117,"column":1},"end":{"line":122,"column":1}},"children":[{"type":"listItem","spread":true,"position":{"start":{"line":117,"column":1},"end":{"line":117,"column":1}},"children":[{"type":"paragraph","children":[{"type":"text","value":"Qualitative/Categorical","position":{"start":{"line":117,"column":1},"end":{"line":117,"column":1}},"key":"QG7dIleqgi"}],"key":"tOTrcsh9uq"}],"key":"QPwvkFuWPZ"},{"type":"listItem","spread":true,"position":{"start":{"line":118,"column":1},"end":{"line":120,"column":1}},"children":[{"type":"paragraph","children":[{"type":"text","value":"Quantitative/Sequential:","position":{"start":{"line":118,"column":1},"end":{"line":118,"column":1}},"key":"OUpV4eiszV"}],"key":"g9nMy2xyI6"},{"type":"list","ordered":false,"spread":false,"position":{"start":{"line":119,"column":1},"end":{"line":120,"column":1}},"children":[{"type":"listItem","spread":true,"position":{"start":{"line":119,"column":1},"end":{"line":119,"column":1}},"children":[{"type":"paragraph","children":[{"type":"text","value":"discrete: Q1, Q2, Q3, Q4; levels after ‘breaks’; age groups...","position":{"start":{"line":119,"column":1},"end":{"line":119,"column":1}},"key":"fIN3NObtGb"}],"key":"Ii8dsbRw5H"}],"key":"HdQOjQSp8E"},{"type":"listItem","spread":true,"position":{"start":{"line":120,"column":1},"end":{"line":120,"column":1}},"children":[{"type":"paragraph","children":[{"type":"text","value":"continuous: scaled data from 0 to 1, with a min-value and max-value, exact age...","position":{"start":{"line":120,"column":1},"end":{"line":120,"column":1}},"key":"v5Cl9TAKMe"}],"key":"AIxl9Eb2M9"}],"key":"TRYOq2FL7F"}],"key":"dfOca9Thsp"}],"key":"hjc1XOe3W3"},{"type":"listItem","spread":true,"position":{"start":{"line":121,"column":1},"end":{"line":121,"column":1}},"children":[{"type":"paragraph","children":[{"type":"text","value":"Diverging: with a center value (e.g., 0)","position":{"start":{"line":121,"column":1},"end":{"line":121,"column":1}},"key":"dIHfMVXLbW"}],"key":"vh00Axa425"}],"key":"pCU3Ft7wRG"},{"type":"listItem","spread":true,"position":{"start":{"line":122,"column":1},"end":{"line":122,"column":1}},"children":[{"type":"paragraph","children":[{"type":"image","url":"/drawing_continuous_d-b948853c1f158fe488018a18ba4412a8.png","width":"40%","key":"xnK0Lp7TRS","urlSource":"resources/w01-img/drawing_continuous_discrete.png"}],"key":"ZvyiIbWZXS"}],"key":"XaAM7Jc067"}],"key":"MBQfWEWzfy"},{"type":"paragraph","position":{"start":{"line":123,"column":1},"end":{"line":123,"column":1}},"children":[{"type":"text","value":"Discrete vs. Continuous.","position":{"start":{"line":123,"column":1},"end":{"line":123,"column":1}},"key":"eNJgGoRBqB"}],"key":"yAZvGT4rdh"}],"key":"wwO7ZWn1N6"},{"type":"listItem","spread":true,"position":{"start":{"line":125,"column":1},"end":{"line":130,"column":1}},"children":[{"type":"paragraph","position":{"start":{"line":125,"column":1},"end":{"line":125,"column":1}},"children":[{"type":"text","value":"Temperature of colors:","position":{"start":{"line":125,"column":1},"end":{"line":125,"column":1}},"key":"emvYR0Jvi0"}],"key":"KMtKFSNCxW"},{"type":"list","ordered":false,"spread":false,"position":{"start":{"line":126,"column":1},"end":{"line":128,"column":1}},"children":[{"type":"listItem","spread":true,"position":{"start":{"line":126,"column":1},"end":{"line":126,"column":1}},"children":[{"type":"paragraph","children":[{"type":"text","value":"cold colors for low values,","position":{"start":{"line":126,"column":1},"end":{"line":126,"column":1}},"key":"pdehBqr6mM"}],"key":"l1H91zUNNH"}],"key":"PXG64MIvCs"},{"type":"listItem","spread":true,"position":{"start":{"line":127,"column":1},"end":{"line":127,"column":1}},"children":[{"type":"paragraph","children":[{"type":"text","value":"hot colors for high values, etc.","position":{"start":{"line":127,"column":1},"end":{"line":127,"column":1}},"key":"pUrjf96CId"}],"key":"O52UjLcjLY"}],"key":"Rv0LXsCXSE"},{"type":"listItem","spread":true,"position":{"start":{"line":128,"column":1},"end":{"line":128,"column":1}},"children":[{"type":"paragraph","children":[{"type":"image","url":"/temperature-of-greys-11f3d132b76de4adef1ca8261215b352.png","width":"40%","key":"xjJZHwMC8b","urlSource":"resources/w01-img/temperature-of-greys.png"}],"key":"XgWxBDVXMs"}],"key":"KpEdqpuTNm"}],"key":"L6jMNF57JO"},{"type":"paragraph","position":{"start":{"line":129,"column":1},"end":{"line":129,"column":1}},"children":[{"type":"link","url":"https://en.wikipedia.org/wiki/Color_temperature","position":{"start":{"line":129,"column":1},"end":{"line":129,"column":1}},"children":[{"type":"text","value":"Color temperature","position":{"start":{"line":129,"column":1},"end":{"line":129,"column":1}},"key":"lpdRT3HtAt"}],"urlSource":"https://en.wikipedia.org/wiki/Color_temperature","data":{"page":"Color_temperature","wiki":"https://en.wikipedia.org/","lang":"en"},"internal":false,"protocol":"wiki","key":"AsxqpxZjmx"},{"type":"text","value":" from Wikipedia.","position":{"start":{"line":129,"column":1},"end":{"line":129,"column":1}},"key":"POgGW1gvOj"}],"key":"ResTpdv8yo"}],"key":"czvN5qmsix"},{"type":"listItem","spread":true,"position":{"start":{"line":131,"column":1},"end":{"line":134,"column":1}},"children":[{"type":"list","ordered":false,"spread":false,"position":{"start":{"line":131,"column":1},"end":{"line":134,"column":1}},"children":[{"type":"listItem","spread":true,"position":{"start":{"line":131,"column":1},"end":{"line":134,"column":1}},"children":[{"type":"paragraph","children":[{"type":"text","value":"The meaning of data:","position":{"start":{"line":131,"column":1},"end":{"line":131,"column":1}},"key":"KcR48coq7x"}],"key":"SlC4WvJCtV"},{"type":"list","ordered":false,"spread":false,"position":{"start":{"line":132,"column":1},"end":{"line":134,"column":1}},"children":[{"type":"listItem","spread":true,"position":{"start":{"line":132,"column":1},"end":{"line":132,"column":1}},"children":[{"type":"paragraph","children":[{"type":"text","value":"green-series colors for greeneries level, or safety level, etc.","position":{"start":{"line":132,"column":1},"end":{"line":132,"column":1}},"key":"Utfqkb4OYw"}],"key":"qsDFwvWLaD"}],"key":"h37Ic6GWkD"},{"type":"listItem","spread":true,"position":{"start":{"line":133,"column":1},"end":{"line":134,"column":1}},"children":[{"type":"paragraph","children":[{"type":"text","value":"red, orange colors for dangerous level, or warning level...","position":{"start":{"line":133,"column":1},"end":{"line":133,"column":1}},"key":"CxfR0ZUFbh"}],"key":"su1CA8BQ5e"}],"key":"OxHypHTPkM"}],"key":"bldc9lGUL2"}],"key":"fPyyerX9Qa"}],"key":"y7vBfGN3ap"}],"key":"OUA9mwVvez"}],"key":"El561YZH8b"},{"type":"container","kind":"figure","children":[{"type":"image","url":"/matplotlib-colors-227b2dcdc446e1bdc086564ad5043b20.png","alt":"colormaps from Matplotlib","align":"center","key":"kI2T2OVN1q","urlSource":"./resources/w01-img/matplotlib-colors.png"},{"type":"caption","children":[{"type":"paragraph","position":{"start":{"line":140,"column":1},"end":{"line":140,"column":1}},"children":[{"type":"captionNumber","kind":"figure","label":"cmap","identifier":"cmap","html_id":"cmap","enumerator":"6","children":[{"type":"text","value":"Figure ","key":"oHRgtwgTB8"},{"type":"text","value":"6","key":"rmV9wEgPof"},{"type":"text","value":":","key":"tk7A5qJVFE"}],"template":"Figure %s:","key":"lHkE61ZJ60"},{"type":"text","value":"Some example of colormaps from ","position":{"start":{"line":140,"column":1},"end":{"line":140,"column":1}},"key":"o1nrHFKVCr"},{"type":"link","url":"https://matplotlib.org/stable/users/explain/colors/colormaps.html","position":{"start":{"line":140,"column":1},"end":{"line":140,"column":1}},"children":[{"type":"text","value":"Matplotlib","position":{"start":{"line":140,"column":1},"end":{"line":140,"column":1}},"key":"K3oKrM8VHc"}],"urlSource":"https://matplotlib.org/stable/users/explain/colors/colormaps.html","key":"ra8BuGy5XB"},{"type":"text","value":".","position":{"start":{"line":140,"column":1},"end":{"line":140,"column":1}},"key":"z2mXSAchjN"}],"key":"m47htQZ0Ph"}],"key":"Kp3XWuPHOW"}],"label":"cmap","identifier":"cmap","enumerator":"6","html_id":"cmap","key":"tiVXurwTjG"},{"type":"container","kind":"figure","children":[{"type":"image","url":"/seaborn-qualitative-17ecf7c55f6afe99c9bfc8ad07e14ea4.png","alt":"qualitative colormap from seaborn","align":"center","key":"qKk6HrfUvM","urlSource":"./resources/w01-img/seaborn-qualitative.png"},{"type":"caption","children":[{"type":"paragraph","position":{"start":{"line":149,"column":1},"end":{"line":149,"column":1}},"children":[{"type":"captionNumber","kind":"figure","label":"seabornquali","identifier":"seabornquali","html_id":"seabornquali","enumerator":"7","children":[{"type":"text","value":"Figure ","key":"dFVio2sJwF"},{"type":"text","value":"7","key":"fK3PlV04JS"},{"type":"text","value":":","key":"Nw4E3I0ig9"}],"template":"Figure %s:","key":"HgUK1vAAaV"},{"type":"text","value":"Various qualitative colormap from ","position":{"start":{"line":149,"column":1},"end":{"line":149,"column":1}},"key":"oOaYwXn9bt"},{"type":"link","url":"https://seaborn.pydata.org/tutorial/color_palettes.html","position":{"start":{"line":149,"column":1},"end":{"line":149,"column":1}},"children":[{"type":"text","value":"Seaborn","position":{"start":{"line":149,"column":1},"end":{"line":149,"column":1}},"key":"kvjI6ZiHHn"}],"urlSource":"https://seaborn.pydata.org/tutorial/color_palettes.html","key":"tmL1AmWdZ9"},{"type":"text","value":".","position":{"start":{"line":149,"column":1},"end":{"line":149,"column":1}},"key":"fAjHxtMKH6"}],"key":"Jc6yGiqWt8"}],"key":"kB7mHa4wek"}],"label":"seabornquali","identifier":"seabornquali","enumerator":"7","html_id":"seabornquali","key":"uk7eNZVlCu"},{"type":"paragraph","position":{"start":{"line":154,"column":1},"end":{"line":154,"column":1}},"children":[{"type":"text","value":"Two basic color models:","position":{"start":{"line":154,"column":1},"end":{"line":154,"column":1}},"key":"PB0nQSKHA1"}],"key":"CmOXVrfVAb"},{"type":"list","ordered":false,"spread":false,"position":{"start":{"line":155,"column":1},"end":{"line":159,"column":1}},"children":[{"type":"listItem","spread":true,"position":{"start":{"line":155,"column":1},"end":{"line":156,"column":1}},"children":[{"type":"paragraph","children":[{"type":"strong","position":{"start":{"line":155,"column":1},"end":{"line":155,"column":1}},"children":[{"type":"text","value":"CMYK","position":{"start":{"line":155,"column":1},"end":{"line":155,"column":1}},"key":"BKVVeLU9yh"}],"key":"d3uHUxbygT"},{"type":"text","value":": allows for more precise control over how colors appear on printed materials.","position":{"start":{"line":155,"column":1},"end":{"line":155,"column":1}},"key":"jRsnIDC9I2"}],"key":"zVmwil8JGb"},{"type":"list","ordered":false,"spread":false,"position":{"start":{"line":156,"column":1},"end":{"line":156,"column":1}},"children":[{"type":"listItem","spread":true,"position":{"start":{"line":156,"column":1},"end":{"line":156,"column":1}},"children":[{"type":"paragraph","children":[{"type":"text","value":"four integer values ranging from 0 to 100, each value corresponding to the percentage of ink coverage for Cyan, Magenta, Yellow, and blacK components.","position":{"start":{"line":156,"column":1},"end":{"line":156,"column":1}},"key":"I3mpnOCwPx"}],"key":"CZ4UCkZIcd"}],"key":"wTutxnOonC"}],"key":"tBjMawGfzr"}],"key":"BnInQw58qs"},{"type":"listItem","spread":true,"position":{"start":{"line":157,"column":1},"end":{"line":159,"column":1}},"children":[{"type":"paragraph","children":[{"type":"strong","position":{"start":{"line":157,"column":1},"end":{"line":157,"column":1}},"children":[{"type":"text","value":"RGB","position":{"start":{"line":157,"column":1},"end":{"line":157,"column":1}},"key":"WeTXYtxUpM"}],"key":"C9YaVgbUz3"},{"type":"text","value":": allows for precise control over how colors appear on digital devices.","position":{"start":{"line":157,"column":1},"end":{"line":157,"column":1}},"key":"ETGFKh9Bak"}],"key":"fdEQjVLUrh"},{"type":"list","ordered":false,"spread":false,"position":{"start":{"line":158,"column":1},"end":{"line":159,"column":1}},"children":[{"type":"listItem","spread":true,"position":{"start":{"line":158,"column":1},"end":{"line":159,"column":1}},"children":[{"type":"paragraph","children":[{"type":"text","value":"three integer values ranging from 0 to 255, each value corresponding to the intensity of the Red, Green, and Blue lights.","position":{"start":{"line":158,"column":1},"end":{"line":158,"column":1}},"key":"TmQ31DE5UX"}],"key":"XhJFTZaHT1"}],"key":"z2SWibgpMZ"}],"key":"dxNk37D61z"}],"key":"Jd0sGQ8dIX"}],"key":"DEvRD8BrrA"},{"type":"paragraph","position":{"start":{"line":160,"column":1},"end":{"line":160,"column":1}},"children":[{"type":"text","value":"How to use colors in Python (Matplotlib):","position":{"start":{"line":160,"column":1},"end":{"line":160,"column":1}},"key":"dXpkiefVx9"}],"key":"FHBH7abM3l"},{"type":"list","ordered":false,"spread":false,"position":{"start":{"line":161,"column":1},"end":{"line":168,"column":1}},"children":[{"type":"listItem","spread":true,"position":{"start":{"line":161,"column":1},"end":{"line":161,"column":1}},"children":[{"type":"paragraph","children":[{"type":"text","value":"named colors: ","position":{"start":{"line":161,"column":1},"end":{"line":161,"column":1}},"key":"ihiuJTzDIh"},{"type":"inlineCode","value":"'red'","position":{"start":{"line":161,"column":1},"end":{"line":161,"column":1}},"key":"l84jqCvAQG"},{"type":"text","value":", ","position":{"start":{"line":161,"column":1},"end":{"line":161,"column":1}},"key":"czVMjKWZ30"},{"type":"inlineCode","value":"'blue'","position":{"start":{"line":161,"column":1},"end":{"line":161,"column":1}},"key":"OT5z3rFkUd"},{"type":"text","value":", ","position":{"start":{"line":161,"column":1},"end":{"line":161,"column":1}},"key":"MhgVYLVEeC"},{"type":"inlineCode","value":"'green'","position":{"start":{"line":161,"column":1},"end":{"line":161,"column":1}},"key":"e3Zp4srKZw"},{"type":"text","value":", ","position":{"start":{"line":161,"column":1},"end":{"line":161,"column":1}},"key":"lLiexd1hmz"},{"type":"inlineCode","value":"'white'","position":{"start":{"line":161,"column":1},"end":{"line":161,"column":1}},"key":"fHAbaP0SHz"},{"type":"text","value":", ","position":{"start":{"line":161,"column":1},"end":{"line":161,"column":1}},"key":"E1LFCj7k49"},{"type":"link","url":"https://matplotlib.org/stable/gallery/color/named_colors.html","position":{"start":{"line":161,"column":1},"end":{"line":161,"column":1}},"children":[{"type":"text","value":"full list here","position":{"start":{"line":161,"column":1},"end":{"line":161,"column":1}},"key":"koJRdEdljH"}],"urlSource":"https://matplotlib.org/stable/gallery/color/named_colors.html","key":"M0xOKy2kWx"}],"key":"tnToDlpxUI"}],"key":"PmqQXRcAVg"},{"type":"listItem","spread":true,"position":{"start":{"line":162,"column":1},"end":{"line":162,"column":1}},"children":[{"type":"paragraph","children":[{"type":"text","value":"xkcd colors: ","position":{"start":{"line":162,"column":1},"end":{"line":162,"column":1}},"key":"YKuJSGIEb5"},{"type":"inlineCode","value":"'xkcd:off white'","position":{"start":{"line":162,"column":1},"end":{"line":162,"column":1}},"key":"w5KQmDXoW8"},{"type":"text","value":", ","position":{"start":{"line":162,"column":1},"end":{"line":162,"column":1}},"key":"dRx98eBpdM"},{"type":"link","url":"https://xkcd.com/color/rgb/","position":{"start":{"line":162,"column":1},"end":{"line":162,"column":1}},"children":[{"type":"text","value":"full list here","position":{"start":{"line":162,"column":1},"end":{"line":162,"column":1}},"key":"K6khKenAt2"}],"urlSource":"https://xkcd.com/color/rgb/","key":"MQq697ELBx"}],"key":"Qd1amJdZuK"}],"key":"SswBgUwLUj"},{"type":"listItem","spread":true,"position":{"start":{"line":163,"column":1},"end":{"line":163,"column":1}},"children":[{"type":"paragraph","children":[{"type":"text","value":"specifying R, G, & B in the ranging from 0 to 1 (divided by 255): ","position":{"start":{"line":163,"column":1},"end":{"line":163,"column":1}},"key":"JKd37sR3NE"},{"type":"inlineCode","value":"(0.1, 0.2, 0.5)","position":{"start":{"line":163,"column":1},"end":{"line":163,"column":1}},"key":"CWOSnASnXz"}],"key":"hLQeZpkgOf"}],"key":"O0QHwruxBj"},{"type":"listItem","spread":true,"position":{"start":{"line":164,"column":1},"end":{"line":164,"column":1}},"children":[{"type":"paragraph","children":[{"type":"text","value":"specifying R, G, B, & alpha in the ranging from 0 to 1 (alpha as proportion): ","position":{"start":{"line":164,"column":1},"end":{"line":164,"column":1}},"key":"iwfRcrCAvp"},{"type":"inlineCode","value":"(0.1, 0.2, 0.5, 0.7)","position":{"start":{"line":164,"column":1},"end":{"line":164,"column":1}},"key":"bkbkRovpK3"}],"key":"TfVQobAuID"}],"key":"jdDNwxKAEw"},{"type":"listItem","spread":true,"position":{"start":{"line":165,"column":1},"end":{"line":165,"column":1}},"children":[{"type":"paragraph","children":[{"type":"text","value":"specifying RGB hex code: ","position":{"start":{"line":165,"column":1},"end":{"line":165,"column":1}},"key":"a1d683yRht"},{"type":"inlineCode","value":"'#0f0f0f'","position":{"start":{"line":165,"column":1},"end":{"line":165,"column":1}},"key":"wDKj3IPnId"}],"key":"xrx6b8ZMA0"}],"key":"anApKEhsNo"},{"type":"listItem","spread":true,"position":{"start":{"line":166,"column":1},"end":{"line":168,"column":1}},"children":[{"type":"paragraph","children":[{"type":"text","value":"specifying RGBA hex code: ","position":{"start":{"line":166,"column":1},"end":{"line":166,"column":1}},"key":"u6lKYWEzz9"},{"type":"inlineCode","value":"'#0f0f0fff'","position":{"start":{"line":166,"column":1},"end":{"line":166,"column":1}},"key":"Dk0uLii5Eb"}],"key":"J8CFjnJTnf"}],"key":"uRjNINjalG"}],"key":"RcnNCcfUJs"},{"type":"heading","depth":2,"position":{"start":{"line":169,"column":1},"end":{"line":169,"column":1}},"children":[{"type":"text","value":"Coordinate System","position":{"start":{"line":169,"column":1},"end":{"line":169,"column":1}},"key":"csHTX0hHGr"}],"identifier":"coordinate-system","label":"Coordinate System","html_id":"coordinate-system","implicit":true,"key":"dr4RLpz5nB"},{"type":"paragraph","position":{"start":{"line":171,"column":1},"end":{"line":171,"column":1}},"children":[{"type":"text","value":"All maps are drawn with a specific coordinate reference system (CRS), which defines how the geographic coordinates of features on the Earth’s surface are represented in a flat, two-dimensional plane (i.e., map). There are two main types of CRS: unprojected and projected.","position":{"start":{"line":171,"column":1},"end":{"line":171,"column":1}},"key":"PtIS64BFjv"}],"key":"Sqnz1RdIOp"},{"type":"list","ordered":true,"start":1,"spread":false,"position":{"start":{"line":173,"column":1},"end":{"line":187,"column":1}},"children":[{"type":"listItem","spread":true,"position":{"start":{"line":173,"column":1},"end":{"line":177,"column":1}},"children":[{"type":"paragraph","position":{"start":{"line":173,"column":1},"end":{"line":173,"column":1}},"children":[{"type":"strong","position":{"start":{"line":173,"column":1},"end":{"line":173,"column":1}},"children":[{"type":"text","value":"Unprojected CRS","position":{"start":{"line":173,"column":1},"end":{"line":173,"column":1}},"key":"GasVMxggrD"}],"key":"PxmgOOLeOb"}],"key":"MiuXNVoaMA"},{"type":"list","ordered":false,"spread":false,"position":{"start":{"line":175,"column":1},"end":{"line":177,"column":1}},"children":[{"type":"listItem","spread":true,"position":{"start":{"line":175,"column":1},"end":{"line":175,"column":1}},"children":[{"type":"paragraph","children":[{"type":"text","value":"Uses latitude (N-S) and longitude (E-W) coordinates in degrees.","position":{"start":{"line":175,"column":1},"end":{"line":175,"column":1}},"key":"PCLC1HBC9N"}],"key":"qXytIGiZv3"}],"key":"Sa980TZkho"},{"type":"listItem","spread":true,"position":{"start":{"line":176,"column":1},"end":{"line":177,"column":1}},"children":[{"type":"paragraph","children":[{"type":"text","value":"Represents Earth’s curved surface.","position":{"start":{"line":176,"column":1},"end":{"line":176,"column":1}},"key":"WZLPjJA6Uc"}],"key":"oPYqQWSnWJ"}],"key":"ks1uS53eeP"}],"key":"xcJdWOWzT4"}],"key":"pYagP3KaDI"},{"type":"listItem","spread":true,"position":{"start":{"line":178,"column":1},"end":{"line":187,"column":1}},"children":[{"type":"paragraph","position":{"start":{"line":178,"column":1},"end":{"line":178,"column":1}},"children":[{"type":"strong","position":{"start":{"line":178,"column":1},"end":{"line":178,"column":1}},"children":[{"type":"text","value":"Projected CRS","position":{"start":{"line":178,"column":1},"end":{"line":178,"column":1}},"key":"tVFCmCO9sJ"}],"key":"Oihho8kvZO"}],"key":"CdHFDYG8n9"},{"type":"list","ordered":false,"spread":false,"position":{"start":{"line":180,"column":1},"end":{"line":185,"column":1}},"children":[{"type":"listItem","spread":true,"position":{"start":{"line":180,"column":1},"end":{"line":180,"column":1}},"children":[{"type":"paragraph","children":[{"type":"text","value":"Transforms Earth’s curved surface into a flat map (in length, e.g. meters).","position":{"start":{"line":180,"column":1},"end":{"line":180,"column":1}},"key":"VLRWCoXgJq"}],"key":"RmsBCCDnEL"}],"key":"faOMFZBA9O"},{"type":"listItem","spread":true,"position":{"start":{"line":181,"column":1},"end":{"line":185,"column":1}},"children":[{"type":"paragraph","children":[{"type":"text","value":"Different types:","position":{"start":{"line":181,"column":1},"end":{"line":181,"column":1}},"key":"tsPGXYMTPQ"}],"key":"Z9p5wL3Ly8"},{"type":"list","ordered":false,"spread":false,"position":{"start":{"line":182,"column":1},"end":{"line":185,"column":1}},"children":[{"type":"listItem","spread":true,"position":{"start":{"line":182,"column":1},"end":{"line":182,"column":1}},"children":[{"type":"paragraph","children":[{"type":"strong","position":{"start":{"line":182,"column":1},"end":{"line":182,"column":1}},"children":[{"type":"text","value":"Mercator","position":{"start":{"line":182,"column":1},"end":{"line":182,"column":1}},"key":"NrjhtZyPZ4"}],"key":"eVa0dVENul"},{"type":"text","value":": Preserves angles and directions, used in navigation.","position":{"start":{"line":182,"column":1},"end":{"line":182,"column":1}},"key":"pRpSK4oU0p"}],"key":"VFNOwfWMPV"}],"key":"JSK8B46ZE2"},{"type":"listItem","spread":true,"position":{"start":{"line":183,"column":1},"end":{"line":183,"column":1}},"children":[{"type":"paragraph","children":[{"type":"strong","position":{"start":{"line":183,"column":1},"end":{"line":183,"column":1}},"children":[{"type":"text","value":"Equal Area","position":{"start":{"line":183,"column":1},"end":{"line":183,"column":1}},"key":"jY8uRle9Tk"}],"key":"Q8ZgP1WWLL"},{"type":"text","value":": Preserves area, useful for spatial analysis.","position":{"start":{"line":183,"column":1},"end":{"line":183,"column":1}},"key":"f9xONRI2SC"}],"key":"QiGboFSYHp"}],"key":"YNqpNRVbWP"},{"type":"listItem","spread":true,"position":{"start":{"line":184,"column":1},"end":{"line":185,"column":1}},"children":[{"type":"paragraph","children":[{"type":"strong","position":{"start":{"line":184,"column":1},"end":{"line":184,"column":1}},"children":[{"type":"text","value":"Conic","position":{"start":{"line":184,"column":1},"end":{"line":184,"column":1}},"key":"SstXVih26B"}],"key":"eHfwap8M1R"},{"type":"text","value":": Preserves shape and angles, used for mid-latitude regions.","position":{"start":{"line":184,"column":1},"end":{"line":184,"column":1}},"key":"RF1VpVSCyc"}],"key":"QAt9rvX1ET"}],"key":"tBqj92iAvl"}],"key":"z8aONBgKeW"}],"key":"HlOisjQlJL"}],"key":"LoeG0PlNmj"},{"type":"paragraph","position":{"start":{"line":186,"column":1},"end":{"line":186,"column":1}},"children":[{"type":"text","value":"Each map projection serves different purposes and has its own advantages and disadvantages in terms of preserving shape, area, distance, and direction. The choice of projection depends on the specific needs and applications of the map.","position":{"start":{"line":186,"column":1},"end":{"line":186,"column":1}},"key":"kHy8lv4y3F"}],"key":"vNZ9xFjx4m"}],"key":"zofJh8Ty8b"}],"key":"scvkBc9Y4q"},{"type":"container","kind":"figure","children":[{"type":"image","url":"/morphing_map_project-213abd0fa90ad0a43eb29b946e3848e9.png","alt":"morphing maps","align":"center","key":"QoGree8XE9","urlSource":"./resources/w01-img/morphing_map_project.png"},{"type":"caption","children":[{"type":"paragraph","position":{"start":{"line":193,"column":1},"end":{"line":193,"column":1}},"children":[{"type":"captionNumber","kind":"figure","label":"morphing","identifier":"morphing","html_id":"morphing","enumerator":"8","children":[{"type":"text","value":"Figure ","key":"oWBUsRvudR"},{"type":"text","value":"8","key":"kZtcVKDKAE"},{"type":"text","value":":","key":"vqJXvlKwOp"}],"template":"Figure %s:","key":"YU2TeXE48c"},{"type":"text","value":"[Try and view the differences of various projections in ","position":{"start":{"line":193,"column":1},"end":{"line":193,"column":1}},"key":"IdIMJdecMx"},{"type":"link","url":"https://wcchin.github.io/map_projection/","position":{"start":{"line":193,"column":1},"end":{"line":193,"column":1}},"children":[{"type":"text","value":"The Morphing Map Project","position":{"start":{"line":193,"column":1},"end":{"line":193,"column":1}},"key":"TgHh3T8pTY"}],"urlSource":"https://wcchin.github.io/map_projection/","key":"gVrdU3GMEY"},{"type":"text","value":".","position":{"start":{"line":193,"column":1},"end":{"line":193,"column":1}},"key":"WMvsDTyjYX"}],"key":"ABrzQX7tHN"}],"key":"txWXUNIeqZ"}],"label":"morphing","identifier":"morphing","enumerator":"8","html_id":"morphing","key":"MI7smY7S2R"},{"type":"container","kind":"figure","children":[{"type":"image","url":"/varying_projections-ed185dc0e350aca1f635a25b16952b4a.png","alt":"Countries in differet projection. ","align":"center","key":"aR6deRm3CT","urlSource":"./resources/w01-img/varying_projections.png"},{"type":"caption","children":[{"type":"paragraph","position":{"start":{"line":202,"column":1},"end":{"line":202,"column":1}},"children":[{"type":"captionNumber","kind":"figure","label":"country_dif","identifier":"country_dif","html_id":"country-dif","enumerator":"9","children":[{"type":"text","value":"Figure ","key":"fow2ZQKJfm"},{"type":"text","value":"9","key":"NhZAlGVxcz"},{"type":"text","value":":","key":"lp9dLSIW7Y"}],"template":"Figure %s:","key":"HPx4gYiQrr"},{"type":"text","value":"The four countries in three different projections.","position":{"start":{"line":202,"column":1},"end":{"line":202,"column":1}},"key":"zlfsch7qP2"}],"key":"ozmyxBGPvp"}],"key":"RIWkZblXsX"}],"label":"country_dif","identifier":"country_dif","enumerator":"9","html_id":"country-dif","key":"KHo24rJzmv"},{"type":"heading","depth":3,"position":{"start":{"line":207,"column":1},"end":{"line":207,"column":1}},"children":[{"type":"text","value":"How to use CRS in Python","position":{"start":{"line":207,"column":1},"end":{"line":207,"column":1}},"key":"SI7xZ1KNro"}],"identifier":"how-to-use-crs-in-python","label":"How to use CRS in Python","html_id":"how-to-use-crs-in-python","implicit":true,"key":"H8vOadHkEG"},{"type":"code","lang":"python","value":"import geopandas as gpd\n# read the file\nsingapore = gpd.read_file('../path_to_file/singapore.shp')\nprint(singapore.crs)  # to show the projection info from the saved file\n\n# use .to_crs() to convert between projections, usually from or to EPSG:4326\n\n# check EPSG.io website, 3414 is the code for SVY21 / Singapore TM,\n# TM means Transverse Mercator, see https://epsg.io/3414 for details\nsg_prjd = singapore.to_crs('epsg:3414')\n# OR\n## find the targeted crs string, something look like this:\ntargeted_crs = '+proj=tmerc +lat_0=1.36666666666667 +lon_0=103.833333333333 +k=1 +x_0=28001.642 +y_0=38744.572 +ellps=WGS84 +towgs84=0,0,0,0,0,0,0 +units=m +no_defs +type=crs'\nsg_prjd = singapore.to_crs(targeted_crs)\n","position":{"start":{"line":209,"column":1},"end":{"line":225,"column":1}},"key":"W0SjJVgQ93"},{"type":"heading","depth":2,"position":{"start":{"line":229,"column":1},"end":{"line":229,"column":1}},"children":[{"type":"text","value":"Arrangement","position":{"start":{"line":229,"column":1},"end":{"line":229,"column":1}},"key":"otPqGvsNQf"}],"identifier":"arrangement","label":"Arrangement","html_id":"arrangement","implicit":true,"key":"JrHbzxtppY"},{"type":"list","ordered":false,"spread":false,"position":{"start":{"line":231,"column":1},"end":{"line":245,"column":1}},"children":[{"type":"listItem","spread":true,"position":{"start":{"line":231,"column":1},"end":{"line":232,"column":1}},"children":[{"type":"paragraph","children":[{"type":"strong","position":{"start":{"line":231,"column":1},"end":{"line":231,"column":1}},"children":[{"type":"text","value":"Arrangement","position":{"start":{"line":231,"column":1},"end":{"line":231,"column":1}},"key":"kCS0KZ5d9q"}],"key":"ToQ4xO3p6n"},{"type":"text","value":" is about the position of every element on map.","position":{"start":{"line":231,"column":1},"end":{"line":231,"column":1}},"key":"PLw6aNzJ7B"}],"key":"sVlLJjUtwr"},{"type":"list","ordered":false,"spread":false,"position":{"start":{"line":232,"column":1},"end":{"line":232,"column":1}},"children":[{"type":"listItem","spread":true,"position":{"start":{"line":232,"column":1},"end":{"line":232,"column":1}},"children":[{"type":"paragraph","children":[{"type":"text","value":"Where to put what","position":{"start":{"line":232,"column":1},"end":{"line":232,"column":1}},"key":"fqUJFHQaKq"}],"key":"FKZ41hf3em"}],"key":"aEMIvspopi"}],"key":"ZOuEuoLbjx"}],"key":"jTmNI1YBVg"},{"type":"listItem","spread":true,"position":{"start":{"line":233,"column":1},"end":{"line":234,"column":1}},"children":[{"type":"paragraph","children":[{"type":"strong","position":{"start":{"line":233,"column":1},"end":{"line":233,"column":1}},"children":[{"type":"text","value":"Which area","position":{"start":{"line":233,"column":1},"end":{"line":233,"column":1}},"key":"mnnjvkA6M6"}],"key":"bq42BVdkvI"},{"type":"text","value":" of a map/paper will be seen first by the readers?","position":{"start":{"line":233,"column":1},"end":{"line":233,"column":1}},"key":"uhuvVVQ7Uw"}],"key":"lqluP8J6Xh"},{"type":"list","ordered":false,"spread":false,"position":{"start":{"line":234,"column":1},"end":{"line":234,"column":1}},"children":[{"type":"listItem","spread":true,"position":{"start":{"line":234,"column":1},"end":{"line":234,"column":1}},"children":[{"type":"paragraph","children":[{"type":"text","value":"The hierarchy of information","position":{"start":{"line":234,"column":1},"end":{"line":234,"column":1}},"key":"UBFjICPSNR"}],"key":"ZSLo6CMqhZ"}],"key":"Csew2rUaZe"}],"key":"X3DAme4KGm"}],"key":"R1mw1bXk8c"},{"type":"listItem","spread":true,"position":{"start":{"line":235,"column":1},"end":{"line":236,"column":1}},"children":[{"type":"paragraph","children":[{"type":"text","value":"Should we draw ","position":{"start":{"line":235,"column":1},"end":{"line":235,"column":1}},"key":"k1q77oYJZr"},{"type":"strong","position":{"start":{"line":235,"column":1},"end":{"line":235,"column":1}},"children":[{"type":"text","value":"North arrow","position":{"start":{"line":235,"column":1},"end":{"line":235,"column":1}},"key":"kcqZWM6PBm"}],"key":"kcp7Dl1Svw"},{"type":"text","value":" and ","position":{"start":{"line":235,"column":1},"end":{"line":235,"column":1}},"key":"Y7YGEfag4K"},{"type":"strong","position":{"start":{"line":235,"column":1},"end":{"line":235,"column":1}},"children":[{"type":"text","value":"scale bar","position":{"start":{"line":235,"column":1},"end":{"line":235,"column":1}},"key":"FVjes0P30E"}],"key":"HGfPyd64zT"},{"type":"text","value":"?","position":{"start":{"line":235,"column":1},"end":{"line":235,"column":1}},"key":"lSa54sP2Mk"}],"key":"B7fvLYzRj0"},{"type":"list","ordered":false,"spread":false,"position":{"start":{"line":236,"column":1},"end":{"line":236,"column":1}},"children":[{"type":"listItem","spread":true,"position":{"start":{"line":236,"column":1},"end":{"line":236,"column":1}},"children":[{"type":"paragraph","children":[{"type":"text","value":"If it is a series of maps, the second and later maps could ignore the N-arrow and scale bar, for the sake of simplicity and readability.","position":{"start":{"line":236,"column":1},"end":{"line":236,"column":1}},"key":"r12klW3Frw"}],"key":"Zrryv9iU3f"}],"key":"J46RyEobjL"}],"key":"Eb3SSK4sY2"}],"key":"ttsKV6ELs0"},{"type":"listItem","spread":true,"position":{"start":{"line":237,"column":1},"end":{"line":238,"column":1}},"children":[{"type":"paragraph","children":[{"type":"strong","position":{"start":{"line":237,"column":1},"end":{"line":237,"column":1}},"children":[{"type":"text","value":"Collective/shared legend","position":{"start":{"line":237,"column":1},"end":{"line":237,"column":1}},"key":"uEyuM9sKF3"}],"key":"YgswwmjaTe"},{"type":"text","value":", or separate legends for every map?","position":{"start":{"line":237,"column":1},"end":{"line":237,"column":1}},"key":"Mm455rlPyn"}],"key":"b5QeygPmv4"},{"type":"list","ordered":false,"spread":false,"position":{"start":{"line":238,"column":1},"end":{"line":238,"column":1}},"children":[{"type":"listItem","spread":true,"position":{"start":{"line":238,"column":1},"end":{"line":238,"column":1}},"children":[{"type":"paragraph","children":[{"type":"text","value":"In a multi-subplots layout setting, the elements in the legend are usually same, so that the colors/sizes could be compared between subplots---in this case, one large shared legend is sufficient.","position":{"start":{"line":238,"column":1},"end":{"line":238,"column":1}},"key":"apmdig4daF"}],"key":"JVYVLN4qwq"}],"key":"Ey9xY9XItX"}],"key":"ywmhvJ1Cyo"}],"key":"UAG4y6PsOe"},{"type":"listItem","spread":true,"position":{"start":{"line":239,"column":1},"end":{"line":241,"column":1}},"children":[{"type":"paragraph","children":[{"type":"text","value":"Figure ","position":{"start":{"line":239,"column":1},"end":{"line":239,"column":1}},"key":"XC52gmbpMp"},{"type":"strong","position":{"start":{"line":239,"column":1},"end":{"line":239,"column":1}},"children":[{"type":"text","value":"title","position":{"start":{"line":239,"column":1},"end":{"line":239,"column":1}},"key":"uetlyMT6jz"}],"key":"Qe6ffzvpJb"}],"key":"haXGvTPmOM"},{"type":"list","ordered":false,"spread":false,"position":{"start":{"line":240,"column":1},"end":{"line":241,"column":1}},"children":[{"type":"listItem","spread":true,"position":{"start":{"line":240,"column":1},"end":{"line":240,"column":1}},"children":[{"type":"paragraph","children":[{"type":"text","value":"Do we need one for a map that would be placed in a report/thesis?","position":{"start":{"line":240,"column":1},"end":{"line":240,"column":1}},"key":"jE2qxs4YQx"}],"key":"lDpFFIASYz"}],"key":"NEDGiCuSAb"},{"type":"listItem","spread":true,"position":{"start":{"line":241,"column":1},"end":{"line":241,"column":1}},"children":[{"type":"paragraph","children":[{"type":"text","value":"It is a common practice that if the map comes with a figure caption (e.g., Fig X. figure title) then the title on top of the map should be removed.","position":{"start":{"line":241,"column":1},"end":{"line":241,"column":1}},"key":"c7JyBsbP9w"}],"key":"yVJAsGkQnL"}],"key":"vRrOGBeXyW"}],"key":"MsFExaeg5h"}],"key":"sqAwhwYGuF"},{"type":"listItem","spread":true,"position":{"start":{"line":242,"column":1},"end":{"line":245,"column":1}},"children":[{"type":"paragraph","children":[{"type":"text","value":"The ","position":{"start":{"line":242,"column":1},"end":{"line":242,"column":1}},"key":"xhAvHQrhQB"},{"type":"strong","position":{"start":{"line":242,"column":1},"end":{"line":242,"column":1}},"children":[{"type":"text","value":"external (out-of-studying-scope) area","position":{"start":{"line":242,"column":1},"end":{"line":242,"column":1}},"key":"yVSDwajwKH"}],"key":"hiuuCMbVXh"}],"key":"d2hqnSu3wJ"},{"type":"list","ordered":false,"spread":false,"position":{"start":{"line":243,"column":1},"end":{"line":245,"column":1}},"children":[{"type":"listItem","spread":true,"position":{"start":{"line":243,"column":1},"end":{"line":245,"column":1}},"children":[{"type":"paragraph","children":[{"type":"text","value":"It is a better idea to draw these external area with light grey or something less attractive.","position":{"start":{"line":243,"column":1},"end":{"line":243,"column":1}},"key":"e0u66VnVV9"}],"key":"aikDd48JVm"}],"key":"Gi0HoI8Rvd"}],"key":"jIV474yvYE"}],"key":"EUCgOmSkET"}],"key":"aS1Fe9WmT9"},{"type":"heading","depth":2,"position":{"start":{"line":246,"column":1},"end":{"line":246,"column":1}},"children":[{"type":"text","value":"Summary","position":{"start":{"line":246,"column":1},"end":{"line":246,"column":1}},"key":"Lzwub8q2Xy"}],"identifier":"summary","label":"Summary","html_id":"summary","implicit":true,"key":"dYvzfNyrMU"},{"type":"paragraph","position":{"start":{"line":247,"column":1},"end":{"line":247,"column":1}},"children":[{"type":"text","value":"Basics of mapping","position":{"start":{"line":247,"column":1},"end":{"line":247,"column":1}},"key":"Ee569KPeR2"}],"key":"ITEx6FCHRm"},{"type":"paragraph","position":{"start":{"line":249,"column":1},"end":{"line":249,"column":1}},"children":[{"type":"text","value":"Things to be considered and planned while visualizing spatial patterns:","position":{"start":{"line":249,"column":1},"end":{"line":249,"column":1}},"key":"sj8CELuGAS"}],"key":"nozKEFCIuo"},{"type":"list","ordered":false,"spread":false,"position":{"start":{"line":250,"column":1},"end":{"line":254,"column":1}},"children":[{"type":"listItem","spread":true,"position":{"start":{"line":250,"column":1},"end":{"line":250,"column":1}},"children":[{"type":"paragraph","children":[{"type":"strong","position":{"start":{"line":250,"column":1},"end":{"line":250,"column":1}},"children":[{"type":"text","value":"Sizes","position":{"start":{"line":250,"column":1},"end":{"line":250,"column":1}},"key":"KazWLmU0X6"}],"key":"asGauMVv8z"},{"type":"text","value":": The sizes of maps and each individual element (line width, point size, etc.) in a static image affect the visibility and aesthetics of the visualization.","position":{"start":{"line":250,"column":1},"end":{"line":250,"column":1}},"key":"YYwko7oMKU"}],"key":"frewv2XOqc"}],"key":"ZLdvMSy1R2"},{"type":"listItem","spread":true,"position":{"start":{"line":251,"column":1},"end":{"line":251,"column":1}},"children":[{"type":"paragraph","children":[{"type":"strong","position":{"start":{"line":251,"column":1},"end":{"line":251,"column":1}},"children":[{"type":"text","value":"Typography","position":{"start":{"line":251,"column":1},"end":{"line":251,"column":1}},"key":"CDtI0n4E2D"}],"key":"Nt4P9BZMJz"},{"type":"text","value":": The visibility of text is the top priority.","position":{"start":{"line":251,"column":1},"end":{"line":251,"column":1}},"key":"uQmi9NQQD8"}],"key":"gPAMSCHg9q"}],"key":"CYTnI0DwNx"},{"type":"listItem","spread":true,"position":{"start":{"line":252,"column":1},"end":{"line":252,"column":1}},"children":[{"type":"paragraph","children":[{"type":"strong","position":{"start":{"line":252,"column":1},"end":{"line":252,"column":1}},"children":[{"type":"text","value":"Colors","position":{"start":{"line":252,"column":1},"end":{"line":252,"column":1}},"key":"gQid9Mw160"}],"key":"QIi5phMJMR"},{"type":"text","value":": Consider the color temperature, relation to the subject, targeted venue, etc.","position":{"start":{"line":252,"column":1},"end":{"line":252,"column":1}},"key":"z61GPgkpuv"}],"key":"BdqD3uDBC1"}],"key":"kRpd3MHVFX"},{"type":"listItem","spread":true,"position":{"start":{"line":253,"column":1},"end":{"line":253,"column":1}},"children":[{"type":"paragraph","children":[{"type":"strong","position":{"start":{"line":253,"column":1},"end":{"line":253,"column":1}},"children":[{"type":"text","value":"Coordinate System","position":{"start":{"line":253,"column":1},"end":{"line":253,"column":1}},"key":"Crs7VRP3eF"}],"key":"RxZoEqH5Ey"},{"type":"text","value":": Choose a commonly used and suitable projection for the targeted area.","position":{"start":{"line":253,"column":1},"end":{"line":253,"column":1}},"key":"Q93NxUB4vZ"}],"key":"EfhMsGSo9M"}],"key":"L1k5Lp8U9f"},{"type":"listItem","spread":true,"position":{"start":{"line":254,"column":1},"end":{"line":254,"column":1}},"children":[{"type":"paragraph","children":[{"type":"strong","position":{"start":{"line":254,"column":1},"end":{"line":254,"column":1}},"children":[{"type":"text","value":"Arrangement","position":{"start":{"line":254,"column":1},"end":{"line":254,"column":1}},"key":"xf7ln1tgZn"}],"key":"GwCROHuOxq"},{"type":"text","value":": Carefully consider the hierarchy of information and the placement of various elements in the map or visualization.","position":{"start":{"line":254,"column":1},"end":{"line":254,"column":1}},"key":"lct1Tox6H5"}],"key":"kSGdKItVEX"}],"key":"SAseOdDrEH"}],"key":"J8y3FwEiqH"}],"key":"wSTS2fRAvm"}],"key":"IGL52e6V1A"},"references":{"cite":{"order":[],"data":{}}}}